{"ar_marker_coordinates": [200, 12, 320, 132], "pages": [{"hyperlinks": [{"uri": "", "coordinates": [72.0, 144.0, 72.0, 144.0]}, {"uri": "", "coordinates": [86.25, 219.0, 109.5, 240.75]}, {"uri": "", "coordinates": [120.0, 285.0, 140.25, 301.5]}, {"uri": "", "coordinates": [244.5, 273.0, 253.5, 282.0]}, {"uri": "", "coordinates": [115.5, 286.5, 124.5, 295.5]}, {"uri": "", "coordinates": [192.0, 300.0, 201.0, 309.0]}, {"uri": "", "coordinates": [129.75, 336.0, 138.75, 345.0]}, {"uri": "", "coordinates": [138.75, 336.0, 147.75, 345.0]}, {"uri": "", "coordinates": [175.5, 414.75, 184.5, 423.75]}, {"uri": "", "coordinates": [150.0, 428.25, 159.0, 437.25]}, {"uri": "", "coordinates": [138.75, 441.0, 147.75, 450.0]}, {"uri": "", "coordinates": [147.75, 441.0, 156.75, 450.0]}, {"uri": "", "coordinates": [206.25, 454.5, 215.25, 463.5]}, {"uri": "", "coordinates": [158.25, 479.25, 171.0, 488.25]}, {"uri": "", "coordinates": [171.0, 479.25, 183.75, 488.25]}, {"uri": "", "coordinates": [240.75, 569.25, 253.5, 578.25]}, {"uri": "", "coordinates": [254.25, 569.25, 267.0, 578.25]}, {"uri": "", "coordinates": [267.0, 569.25, 279.75, 578.25]}, {"uri": "", "coordinates": [108.75, 594.0, 121.5, 603.0]}, {"uri": "", "coordinates": [144.0, 606.75, 156.75, 615.75]}, {"uri": "", "coordinates": [291.75, 666.75, 304.5, 675.75]}, {"uri": "", "coordinates": [266.25, 700.5, 279.0, 709.5]}, {"uri": "", "coordinates": [159.75, 725.25, 172.5, 734.25]}, {"uri": "https://en.wikipedia.org/wiki/Main_Page", "coordinates": [87.75, 189.0, 126.75, 205.5]}, {"uri": "https://en.wikipedia.org/wiki/Wikipedia:Contents", "coordinates": [87.75, 199.5, 121.5, 216.0]}, {"uri": "https://en.wikipedia.org/wiki/Portal:Current_events", "coordinates": [87.75, 210.0, 116.25, 236.25]}, {"uri": "https://en.wikipedia.org/wiki/Special:Random", "coordinates": [87.75, 229.5, 119.25, 255.75]}, {"uri": "https://en.wikipedia.org/wiki/Wikipedia:About", "coordinates": [87.75, 249.0, 123.75, 275.25]}, {"uri": "https://en.wikipedia.org/wiki/Wikipedia:Contact_us", "coordinates": [87.75, 269.25, 128.25, 285.75]}, {"uri": "https://donate.wikimedia.org/wiki/Special:FundraiserRedirector?utm_source=donate&utm_medium=sidebar&utm_campaign=C13_en.wikipedia.org&uselang=en", "coordinates": [87.75, 279.0, 114.75, 295.5]}, {"uri": "https://en.wikipedia.org/wiki/Help:Contents", "coordinates": [87.75, 312.75, 104.25, 329.25]}, {"uri": "https://en.wikipedia.org/wiki/Help:Introduction", "coordinates": [87.75, 323.25, 135.75, 339.75]}, {"uri": "https://en.wikipedia.org/wiki/Wikipedia:Community_portal", "coordinates": [87.75, 333.0, 129.75, 359.25]}, {"uri": "https://en.wikipedia.org/wiki/Special:RecentChanges", "coordinates": [87.75, 353.25, 120.0, 379.5]}, {"uri": "https://en.wikipedia.org/wiki/Wikipedia:File_upload_wizard", "coordinates": [87.75, 372.75, 126.75, 389.25]}, {"uri": "https://en.wikipedia.org/wiki/Main_Page", "coordinates": [86.25, 161.25, 86.25, 161.25]}, {"uri": "https://en.wikipedia.org/wiki/Special:Search", "coordinates": [481.5, 161.25, 507.75, 187.5]}, {"uri": "https://en.wikipedia.org/w/index.php?title=Special:CreateAccount&returnto=Guacamole", "coordinates": [385.5, 182.25, 461.25, 198.75]}, {"uri": "https://en.wikipedia.org/w/index.php?title=Special:UserLogin&returnto=Guacamole", "coordinates": [385.5, 194.25, 426.75, 210.75]}, {"uri": "https://en.wikipedia.org/wiki/Help:Introduction", "coordinates": [385.5, 216.75, 432.0, 225.75]}, {"uri": "https://en.wikipedia.org/wiki/Special:MyContributions", "coordinates": [385.5, 222.75, 435.75, 239.25]}, {"uri": "https://en.wikipedia.org/wiki/Special:MyTalk", "coordinates": [385.5, 232.5, 401.25, 249.0]}, {"uri": "https://af.wikipedia.org/wiki/Guacamole", "coordinates": [443.25, 244.5, 478.5, 261.0]}, {"uri": "https://ar.wikipedia.org/wiki/%25D8%25BA%25D9%2588%25D8%25A7%25D9%2583%25D8%25A7%25D9%2585%25D9%2588%25D9%2584%25D9%258A", "coordinates": [443.25, 255.0, 461.25, 271.5]}, {"uri": "https://az.wikipedia.org/wiki/Quakamole", "coordinates": [443.25, 264.75, 496.5, 281.25]}, {"uri": "https://be.wikipedia.org/wiki/%25D0%2593%25D1%2583%25D0%25B0%25D0%25BA%25D0%25B0%25D0%25BC%25D0%25BE%25D0%25BB%25D0%25B5", "coordinates": [443.25, 275.25, 489.0, 291.75]}, {"uri": "https://be-tarask.wikipedia.org/wiki/%25D0%2593%25D1%2583%25D0%25B0%25D0%25BA%25D0%25B0%25D0%25BC%25D0%25BE%25D0%25BB%25D0%25B5", "coordinates": [443.25, 285.0, 498.75, 311.25]}, {"uri": "https://bg.wikipedia.org/wiki/%25D0%2593%25D1%2583%25D0%25B0%25D0%25BA%25D0%25B0%25D0%25BC%25D0%25BE%25D0%25BB%25D0%25B5", "coordinates": [443.25, 305.25, 483.75, 321.75]}, {"uri": "https://ca.wikipedia.org/wiki/Guacamole", "coordinates": [443.25, 315.0, 467.25, 331.5]}, {"uri": "https://cs.wikipedia.org/wiki/Guacamole", "coordinates": [443.25, 325.5, 471.75, 342.0]}, {"uri": "https://da.wikipedia.org/wiki/Guacamole", "coordinates": [443.25, 336.0, 467.25, 352.5]}, {"uri": "https://de.wikipedia.org/wiki/Guacamole", "coordinates": [443.25, 345.75, 474.0, 362.25]}, {"uri": "https://el.wikipedia.org/wiki/%25CE%2593%25CE%25BF%25CF%2585%25CE%25B1%25CE%25BA%25CE%25B1%25CE%25BC%25CF%258C%25CE%25BB%25CE%25B5", "coordinates": [443.25, 356.25, 476.25, 372.75]}, {"uri": "https://es.wikipedia.org/wiki/Guacamole", "coordinates": [443.25, 366.0, 473.25, 382.5]}, {"uri": "https://eo.wikipedia.org/wiki/Avokada_ka%25C4%2589o", "coordinates": [443.25, 376.5, 482.25, 393.0]}, {"uri": "https://eu.wikipedia.org/wiki/Guacamole", "coordinates": [443.25, 387.0, 474.0, 403.5]}, {"uri": "https://fa.wikipedia.org/wiki/%25DA%25AF%25D9%2588%25D8%25A2%25DA%25A9%25D8%25A7%25D9%2585%25D9%2588%25D9%2584%25D9%2587", "coordinates": [443.25, 396.75, 460.5, 413.25]}, {"uri": "https://fr.wikipedia.org/wiki/Guacamole", "coordinates": [443.25, 407.25, 476.25, 423.75]}, {"uri": "https://gl.wikipedia.org/wiki/Guacamole", "coordinates": [443.25, 417.0, 470.25, 433.5]}, {"uri": "https://ko.wikipedia.org/wiki/%25EA%25B3%25BC%25EC%25B9%25B4%25EB%25AA%25B0%25EB%25A0%2588", "coordinates": [443.25, 427.5, 462.75, 444.0]}, {"uri": "https://hy.wikipedia.org/wiki/%25D4%25B3%25D5%25B8%25D6%2582%25D5%25A1%25D5%25AF%25D5%25A1%25D5%25B4%25D5%25B8%25D5%25AC%25D5%25A5", "coordinates": [443.25, 438.0, 476.25, 454.5]}, {"uri": "https://id.wikipedia.org/wiki/Guacamole", "coordinates": [443.25, 447.75, 479.25, 474.0]}, {"uri": "https://it.wikipedia.org/wiki/Guacamole", "coordinates": [443.25, 468.0, 470.25, 484.5]}, {"uri": "https://he.wikipedia.org/wiki/%25D7%2592%25D7%2595%25D7%2590%25D7%25A7%25D7%259E%25D7%2595%25D7%259C%25D7%2594", "coordinates": [443.25, 477.75, 463.5, 494.25]}, {"uri": "https://jv.wikipedia.org/wiki/Guacamol%25C3%25A9", "coordinates": [443.25, 488.25, 461.25, 504.75]}, {"uri": "https://kn.wikipedia.org/wiki/%25E0%25B2%2597%25E0%25B3%258D%25E0%25B2%25B5%25E0%25B2%25BE%25E0%25B2%2595%25E0%25B2%25AE%25E0%25B3%258B%25E0%25B2%25B2%25E0%25B3%2586", "coordinates": [443.25, 498.0, 485.25, 514.5]}, {"uri": "https://ka.wikipedia.org/wiki/%25E1%2583%2592%25E1%2583%2595%25E1%2583%2590%25E1%2583%25A5%25E1%2583%2590%25E1%2583%259B%25E1%2583%259D%25E1%2583%259A%25E1%2583%2594", "coordinates": [443.25, 508.5, 477.0, 525.0]}, {"uri": "https://la.wikipedia.org/wiki/Guacamole", "coordinates": [443.25, 519.0, 466.5, 535.5]}, {"uri": "https://lt.wikipedia.org/wiki/Gvakamol%25C4%2597", "coordinates": [443.25, 528.75, 472.5, 545.25]}, {"uri": "https://lfn.wikipedia.org/wiki/Guacamole", "coordinates": [443.25, 539.25, 491.25, 565.5]}, {"uri": "https://hu.wikipedia.org/wiki/Guacamole", "coordinates": [443.25, 558.75, 471.0, 575.25]}, {"uri": "https://mk.wikipedia.org/wiki/%25D0%2593%25D0%25B2%25D0%25B0%25D0%25BA%25D0%25B0%25D0%25BC%25D0%25BE%25D0%25BB%25D0%25B5", "coordinates": [443.25, 569.25, 489.75, 585.75]}, {"uri": "https://ms.wikipedia.org/wiki/Guacamole", "coordinates": [443.25, 579.0, 471.75, 605.25]}, {"uri": "https://nah.wikipedia.org/wiki/Ahuacamolli", "coordinates": [443.25, 599.25, 471.75, 615.75]}, {"uri": "https://nl.wikipedia.org/wiki/Guacamole", "coordinates": [443.25, 609.75, 486.0, 626.25]}, {"uri": "https://ja.wikipedia.org/wiki/%25E3%2583%25AF%25E3%2582%25AB%25E3%2583%25A2%25E3%2583%25AC", "coordinates": [443.25, 619.5, 468.0, 636.0]}, {"uri": "https://no.wikipedia.org/wiki/Guacamole", "coordinates": [443.25, 630.0, 470.25, 656.25]}, {"uri": "https://nn.wikipedia.org/wiki/Guacamole", "coordinates": [443.25, 649.5, 473.25, 675.75]}, {"uri": "https://pl.wikipedia.org/wiki/Guacamole", "coordinates": [443.25, 669.75, 465.0, 686.25]}, {"uri": "https://pt.wikipedia.org/wiki/Guacamole", "coordinates": [443.25, 679.5, 482.25, 696.0]}, {"uri": "https://ro.wikipedia.org/wiki/Guacamole", "coordinates": [443.25, 690.0, 474.75, 706.5]}, {"uri": "https://ru.wikipedia.org/wiki/%25D0%2593%25D1%2583%25D0%25B0%25D0%25BA%25D0%25B0%25D0%25BC%25D0%25BE%25D0%25BB%25D0%25B5", "coordinates": [443.25, 699.75, 474.0, 716.25]}, {"uri": "https://sco.wikipedia.org/wiki/Guacamole", "coordinates": [443.25, 710.25, 464.25, 726.75]}, {"uri": "https://simple.wikipedia.org/wiki/Guacamole", "coordinates": [443.25, 720.75, 470.25, 747.0]}, {"uri": "https://sr.wikipedia.org/wiki/%25D0%2593%25D0%25B2%25D0%25B0%25D0%25BA%25D0%25B0%25D0%25BC%25D0%25BE%25D0%25BB%25D0%25B5", "coordinates": [443.25, 740.25, 476.25, 766.5]}, {"uri": "https://su.wikipedia.org/wiki/Guacamole", "coordinates": [443.25, 759.75, 467.25, 776.25]}, {"uri": "https://en.wikipedia.org/wiki/Talk:Guacamole", "coordinates": [119.25, 219.0, 135.0, 240.0]}, {"uri": "https://en.wikipedia.org/w/index.php?title=Guacamole&action=edit", "coordinates": [120.0, 294.75, 134.25, 311.25]}, {"uri": "https://en.wikipedia.org/w/index.php?title=Guacamole&action=history", "coordinates": [120.0, 305.25, 144.75, 331.5]}, {"uri": "https://en.wikipedia.org/wiki/Special:WhatLinksHere/Guacamole", "coordinates": [120.0, 348.0, 139.5, 384.0]}, {"uri": "https://en.wikipedia.org/wiki/Special:RecentChangesLinked/Guacamole", "coordinates": [120.0, 378.0, 152.25, 404.25]}, {"uri": "https://en.wikipedia.org/wiki/Special:SpecialPages", "coordinates": [120.0, 397.5, 147.0, 423.75]}, {"uri": "https://en.wikipedia.org/w/index.php?title=Guacamole&oldid=1222302359", "coordinates": [120.0, 417.0, 161.25, 443.25]}, {"uri": "https://en.wikipedia.org/w/index.php?title=Guacamole&action=info", "coordinates": [120.0, 437.25, 162.0, 463.5]}, {"uri": "https://en.wikipedia.org/w/index.php?title=Special:CiteThisPage&page=Guacamole&id=1222302359&wpFormIdentifier=titleform", "coordinates": [120.0, 456.75, 150.0, 483.0]}, {"uri": "https://en.wikipedia.org/w/index.php?title=Special:UrlShortener&url=https%253A%252F%252Fen.wikipedia.org%252Fwiki%252FGuacamole", "coordinates": [120.0, 477.0, 158.25, 513.0]}, {"uri": "https://en.wikipedia.org/w/index.php?title=Special:QrCode&url=https%253A%252F%252Fen.wikipedia.org%252Fwiki%252FGuacamole", "coordinates": [120.0, 506.25, 156.75, 542.25]}, {"uri": "https://www.wikidata.org/wiki/Special:EntityPage/Q207968", "coordinates": [120.0, 535.5, 152.25, 561.75]}, {"uri": "https://en.wikipedia.org/w/index.php?title=Special:DownloadAsPdf&page=Guacamole&action=show-download-screen", "coordinates": [120.0, 579.0, 156.75, 605.25]}, {"uri": "https://commons.wikimedia.org/wiki/Category:Guacamole", "coordinates": [120.0, 631.5, 158.25, 657.75]}, {"uri": "https://en.wikibooks.org/wiki/Cookbook:Guacamole_I", "coordinates": [120.0, 651.75, 158.25, 668.25]}, {"uri": "https://en.wikipedia.org/wiki/File:Guacamole_IMGP1271.jpg", "coordinates": [348.75, 321.75, 480.75, 330.75]}, {"uri": "https://en.wikipedia.org/wiki/Dipping_sauce", "coordinates": [383.25, 414.0, 395.25, 423.0]}, {"uri": "https://en.wikipedia.org/wiki/Mexico", "coordinates": [383.25, 429.0, 408.75, 438.0]}, {"uri": "https://en.wikipedia.org/wiki/Avocado", "coordinates": [383.25, 451.5, 420.0, 460.5]}, {"uri": "https://en.wikipedia.org/wiki/Salt", "coordinates": [425.25, 451.5, 438.0, 460.5]}, {"uri": "https://en.wikipedia.org/wiki/Lime_(fruit)", "coordinates": [443.25, 451.5, 477.75, 460.5]}, {"uri": "https://en.wikipedia.org/wiki/Onion", "coordinates": [383.25, 464.25, 404.25, 473.25]}, {"uri": "https://en.wikipedia.org/wiki/Cilantro", "coordinates": [408.75, 464.25, 435.75, 473.25]}, {"uri": "https://en.wikipedia.org/wiki/Tomato", "coordinates": [441.0, 464.25, 466.5, 473.25]}, {"uri": "https://en.wikipedia.org/wiki/Sour_cream", "coordinates": [383.25, 480.0, 426.75, 489.0]}, {"uri": "https://en.wikipedia.org/wiki/Basil", "coordinates": [432.0, 480.0, 449.25, 489.0]}, {"uri": "https://en.wikipedia.org/wiki/Avocado_sauce", "coordinates": [383.25, 495.0, 441.0, 504.0]}, {"uri": "https://en.wikipedia.org/wiki/Wasakaka", "coordinates": [429.75, 520.5, 471.0, 529.5]}, {"uri": "https://en.wikipedia.org/wiki/File:Wikibooks-logo-en-noslogan.svg", "coordinates": [366.0, 537.75, 375.75, 546.75]}, {"uri": "https://en.wikibooks.org/wiki/Cookbook:Guacamole_I", "coordinates": [378.0, 537.75, 465.0, 546.75]}, {"uri": "https://en.wikipedia.org/wiki/File:Commons-logo.svg", "coordinates": [375.75, 550.5, 383.25, 559.5]}, {"uri": "https://commons.wikimedia.org/wiki/Category:Guacamole", "coordinates": [385.5, 550.5, 456.75, 559.5]}, {"uri": "https://en.wikipedia.org/wiki/Help:IPA/Spanish", "coordinates": [178.5, 261.75, 234.0, 272.25]}, {"uri": "https://upload.wikimedia.org/wikipedia/commons/transcoded/1/14/GuacamolePronunciation.ogg/GuacamolePronunciation.ogg.mp3", "coordinates": [237.0, 261.75, 246.0, 272.25]}, {"uri": "https://en.wikipedia.org/wiki/File:GuacamolePronunciation.ogg", "coordinates": [246.0, 259.5, 253.5, 268.5]}, {"uri": "https://en.wikipedia.org/wiki/Avocado", "coordinates": [149.25, 288.75, 185.25, 299.25]}, {"uri": "https://en.wikipedia.org/wiki/Dip_(food)", "coordinates": [216.75, 288.75, 229.5, 299.25]}, {"uri": "https://en.wikipedia.org/wiki/Salad", "coordinates": [279.75, 288.75, 302.25, 299.25]}, {"uri": "https://en.wikipedia.org/wiki/Mexican_cuisine", "coordinates": [120.0, 313.5, 186.0, 324.0]}, {"uri": "https://en.wikipedia.org/wiki/Condiment", "coordinates": [209.25, 324.75, 252.0, 335.25]}, {"uri": "https://en.wikipedia.org/w/index.php?title=Guacamole&action=edit&section=1", "coordinates": [286.5, 372.0, 298.5, 381.0]}, {"uri": "https://en.wikipedia.org/wiki/File:Guacomole.jpg", "coordinates": [372.0, 575.25, 507.0, 666.75]}, {"uri": "https://en.wikipedia.org/wiki/Classical_Nahuatl", "coordinates": [181.5, 393.0, 253.5, 403.5]}, {"uri": "https://en.wikipedia.org/wiki/Help:IPA/Nahuatl", "coordinates": [86.25, 404.25, 146.25, 414.75]}, {"uri": "https://en.wikipedia.org/wiki/Help:IPA/Nahuatl", "coordinates": [186.75, 417.0, 229.5, 427.5]}, {"uri": "https://en.wikipedia.org/wiki/Help:IPA/Nahuatl", "coordinates": [86.25, 430.5, 116.25, 441.0]}, {"uri": "https://en.wikipedia.org/wiki/Mexican_Spanish", "coordinates": [170.25, 430.5, 241.5, 441.0]}, {"uri": "https://en.wikipedia.org/wiki/Help:IPA/Spanish", "coordinates": [86.25, 444.0, 136.5, 454.5]}, {"uri": "https://en.wikipedia.org/wiki/Help:IPA/English", "coordinates": [138.0, 456.75, 204.0, 467.25]}, {"uri": "https://en.wikipedia.org/wiki/Help:IPA/English", "coordinates": [243.0, 468.0, 312.75, 478.5]}, {"uri": "https://en.wikipedia.org/w/index.php?title=Guacamole&action=edit&section=2", "coordinates": [144.0, 516.0, 156.0, 525.0]}, {"uri": "https://en.wikipedia.org/wiki/Mexico", "coordinates": [96.0, 546.75, 126.0, 557.25]}, {"uri": "https://en.wikipedia.org/wiki/William_Dampier", "coordinates": [86.25, 644.25, 155.25, 654.75]}, {"uri": "https://en.wikipedia.org/wiki/Super_Bowl_Sunday", "coordinates": [99.0, 702.75, 180.0, 713.25]}, {"uri": "https://en.wikipedia.org/wiki/Cinco_de_Mayo", "coordinates": [201.0, 702.75, 264.0, 713.25]}]}, {"hyperlinks": [{"uri": "", "coordinates": [201.0, 189.0, 213.75, 198.0]}, {"uri": "", "coordinates": [213.75, 189.0, 226.5, 198.0]}, {"uri": "", "coordinates": [411.75, 202.5, 424.5, 211.5]}, {"uri": "", "coordinates": [456.0, 237.0, 468.75, 246.0]}, {"uri": "", "coordinates": [291.0, 273.0, 303.75, 282.0]}, {"uri": "", "coordinates": [126.0, 374.25, 138.75, 383.25]}, {"uri": "", "coordinates": [139.5, 374.25, 152.25, 383.25]}, {"uri": "", "coordinates": [468.75, 374.25, 481.5, 383.25]}, {"uri": "", "coordinates": [108.0, 469.5, 120.75, 478.5]}, {"uri": "", "coordinates": [240.0, 483.0, 249.0, 492.0]}, {"uri": "", "coordinates": [189.0, 546.0, 201.75, 555.0]}, {"uri": "", "coordinates": [285.0, 546.0, 297.75, 555.0]}, {"uri": "", "coordinates": [164.25, 571.5, 177.0, 580.5]}, {"uri": "", "coordinates": [147.0, 632.25, 159.75, 641.25]}, {"uri": "", "coordinates": [222.0, 705.0, 234.75, 714.0]}, {"uri": "https://fi.wikipedia.org/wiki/Guacamole", "coordinates": [443.25, 144.0, 466.5, 160.5]}, {"uri": "https://sv.wikipedia.org/wiki/Guacamole", "coordinates": [443.25, 154.5, 475.5, 171.0]}, {"uri": "https://th.wikipedia.org/wiki/%25E0%25B8%2581%25E0%25B8%25B1%25E0%25B8%25A7%25E0%25B8%2581%25E0%25B8%25B2%25E0%25B9%2582%25E0%25B8%25A1%25E0%25B9%2580%25E0%25B8%25A5", "coordinates": [443.25, 165.0, 458.25, 181.5]}, {"uri": "https://tr.wikipedia.org/wiki/Guacamole", "coordinates": [443.25, 174.75, 469.5, 191.25]}, {"uri": "https://uk.wikipedia.org/wiki/%25D0%2593%25D1%2583%25D0%25B0%25D0%25BA%25D0%25B0%25D0%25BC%25D0%25BE%25D0%25BB%25D0%25B5", "coordinates": [443.25, 185.25, 485.25, 201.75]}, {"uri": "https://vi.wikipedia.org/wiki/Guacamole", "coordinates": [443.25, 195.0, 481.5, 211.5]}, {"uri": "https://war.wikipedia.org/wiki/Guacamole", "coordinates": [443.25, 205.5, 474.0, 222.0]}, {"uri": "https://zh-yue.wikipedia.org/wiki/%25E7%2589%259B%25E6%25B2%25B9%25E6%259E%259C%25E9%2586%25AC", "coordinates": [443.25, 216.0, 459.75, 232.5]}, {"uri": "https://zh.wikipedia.org/wiki/%25E9%25B3%2584%25E6%25A2%25A8%25E9%2585%25B1", "coordinates": [443.25, 225.75, 459.75, 242.25]}, {"uri": "https://www.wikidata.org/wiki/Special:EntityPage/Q207968#sitelinks-wikipedia", "coordinates": [429.75, 245.25, 462.75, 254.25]}, {"uri": "https://en.wikipedia.org/w/index.php?title=Guacamole&action=edit&section=3", "coordinates": [169.5, 158.25, 181.5, 167.25]}, {"uri": "https://en.wikipedia.org/wiki/Avocado", "coordinates": [324.0, 178.5, 364.5, 189.0]}, {"uri": "https://en.wikipedia.org/wiki/Salt", "coordinates": [384.75, 178.5, 399.0, 189.0]}, {"uri": "https://en.wikipedia.org/wiki/Molcajete", "coordinates": [86.25, 177.75, 477.0, 201.75]}, {"uri": "https://en.wikipedia.org/wiki/Lime_juice", "coordinates": [318.75, 192.0, 357.75, 202.5]}, {"uri": "https://en.wikipedia.org/wiki/Cilantro", "coordinates": [363.0, 192.0, 393.0, 202.5]}, {"uri": "https://en.wikipedia.org/wiki/Onion", "coordinates": [397.5, 192.0, 424.5, 202.5]}, {"uri": "https://en.wikipedia.org/wiki/Jalape%25C3%25B1o", "coordinates": [447.75, 192.0, 487.5, 202.5]}, {"uri": "https://en.wikipedia.org/wiki/Sour_cream", "coordinates": [258.0, 204.75, 304.5, 215.25]}, {"uri": "https://en.wikipedia.org/wiki/Tomatoes", "coordinates": [309.0, 204.75, 348.0, 215.25]}, {"uri": "https://en.wikipedia.org/wiki/Basil", "coordinates": [353.25, 204.75, 372.75, 215.25]}, {"uri": "https://en.wikipedia.org/wiki/Peas", "coordinates": [388.5, 204.75, 409.5, 215.25]}, {"uri": "https://en.wikipedia.org/wiki/Polyphenol_oxidase", "coordinates": [183.0, 225.75, 262.5, 236.25]}, {"uri": "https://en.wikipedia.org/wiki/Enzymatic_reaction", "coordinates": [131.25, 239.25, 208.5, 249.75]}, {"uri": "https://en.wikipedia.org/wiki/Melanoidin", "coordinates": [269.25, 239.25, 314.25, 249.75]}, {"uri": "https://en.wikipedia.org/w/index.php?title=Guacamole&action=edit&section=4", "coordinates": [267.0, 309.0, 279.0, 318.0]}, {"uri": "https://en.wikipedia.org/wiki/Dietary_fibre", "coordinates": [279.75, 340.5, 328.5, 351.0]}, {"uri": "https://en.wikipedia.org/wiki/B_vitamins", "coordinates": [366.0, 340.5, 408.75, 351.0]}, {"uri": "https://en.wikipedia.org/wiki/Vitamin_K", "coordinates": [414.0, 340.5, 452.25, 351.0]}, {"uri": "https://en.wikipedia.org/wiki/Vitamin_E", "coordinates": [457.5, 340.5, 495.75, 351.0]}, {"uri": "https://en.wikipedia.org/wiki/Potassium", "coordinates": [104.25, 351.75, 147.0, 362.25]}, {"uri": "https://en.wikipedia.org/wiki/Daily_Value", "coordinates": [257.25, 351.75, 304.5, 362.25]}, {"uri": "https://en.wikipedia.org/wiki/Saturated_fat", "coordinates": [195.0, 363.0, 246.0, 373.5]}, {"uri": "https://en.wikipedia.org/wiki/Monounsaturated_fat", "coordinates": [252.0, 363.0, 336.0, 373.5]}, {"uri": "https://en.wikipedia.org/wiki/Phytosterols", "coordinates": [357.0, 363.0, 406.5, 373.5]}, {"uri": "https://en.wikipedia.org/wiki/Beta-sitosterol", "coordinates": [86.25, 363.0, 467.25, 387.0]}, {"uri": "https://en.wikipedia.org/wiki/Carotenoids", "coordinates": [229.5, 376.5, 278.25, 387.0]}, {"uri": "https://en.wikipedia.org/wiki/Beta-carotene", "coordinates": [318.0, 376.5, 375.75, 387.0]}, {"uri": "https://en.wikipedia.org/wiki/Zeaxanthin", "coordinates": [381.0, 376.5, 424.5, 387.0]}, {"uri": "https://en.wikipedia.org/wiki/Lutein", "coordinates": [444.75, 376.5, 465.75, 387.0]}, {"uri": "https://en.wikipedia.org/w/index.php?title=Guacamole&action=edit&section=5", "coordinates": [186.0, 411.0, 198.0, 420.0]}, {"uri": "https://en.wikipedia.org/w/index.php?title=Guacamole&action=edit&section=6", "coordinates": [216.0, 440.25, 228.0, 449.25]}, {"uri": "https://en.wikipedia.org/wiki/Spanish_language", "coordinates": [182.25, 459.0, 216.0, 469.5]}, {"uri": "https://en.wikipedia.org/wiki/Dairy_cattle", "coordinates": [298.5, 471.75, 343.5, 482.25]}, {"uri": "https://en.wikipedia.org/w/index.php?title=Guacamole&action=edit&section=7", "coordinates": [159.0, 514.5, 171.0, 523.5]}, {"uri": "https://en.wikipedia.org/wiki/File:Guasacaca_avocado_sauce-1500x1000.jpg", "coordinates": [348.0, 534.75, 507.0, 642.0]}, {"uri": "https://en.wikipedia.org/wiki/Wasakaka", "coordinates": [156.0, 530.25, 201.0, 541.5]}, {"uri": "https://en.wikipedia.org/wiki/Venezuelan_cuisine", "coordinates": [153.0, 561.0, 201.0, 571.5]}, {"uri": "https://en.wikipedia.org/wiki/Arepa", "coordinates": [112.5, 585.0, 141.75, 596.25]}, {"uri": "https://en.wikipedia.org/wiki/Empanada", "coordinates": [147.0, 585.0, 198.0, 596.25]}, {"uri": "https://en.wikipedia.org/w/index.php?title=Guacamole&action=edit&section=8", "coordinates": [191.25, 663.75, 203.25, 672.75]}, {"uri": "https://en.wikipedia.org/wiki/Summer_squash", "coordinates": [383.25, 693.75, 449.25, 704.25]}, {"uri": "https://en.wikipedia.org/wiki/Green_tomatoes", "coordinates": [86.25, 693.75, 477.75, 717.75]}, {"uri": "https://en.wikipedia.org/w/index.php?title=Guacamole&action=edit&section=9", "coordinates": [234.0, 741.75, 246.0, 750.75]}]}, {"hyperlinks": [{"uri": "", "coordinates": [114.0, 165.75, 126.75, 174.75]}, {"uri": "", "coordinates": [99.0, 233.25, 111.75, 242.25]}, {"uri": "", "coordinates": [112.5, 233.25, 125.25, 242.25]}, {"uri": "", "coordinates": [129.0, 312.0, 141.75, 321.0]}, {"uri": "", "coordinates": [114.0, 526.5, 118.5, 535.5]}, {"uri": "", "coordinates": [114.0, 537.0, 118.5, 546.0]}, {"uri": "", "coordinates": [119.25, 558.0, 123.0, 567.0]}, {"uri": "", "coordinates": [126.0, 558.0, 129.75, 567.0]}, {"uri": "", "coordinates": [119.25, 589.5, 123.0, 598.5]}, {"uri": "", "coordinates": [126.0, 589.5, 129.75, 598.5]}, {"uri": "", "coordinates": [114.0, 618.75, 118.5, 627.75]}, {"uri": "", "coordinates": [114.0, 639.0, 118.5, 648.0]}, {"uri": "", "coordinates": [114.0, 648.75, 118.5, 657.75]}, {"uri": "", "coordinates": [114.0, 669.0, 118.5, 678.0]}, {"uri": "", "coordinates": [114.0, 688.5, 118.5, 697.5]}, {"uri": "", "coordinates": [114.0, 708.75, 118.5, 717.75]}, {"uri": "", "coordinates": [114.0, 728.25, 118.5, 737.25]}, {"uri": "", "coordinates": [114.0, 738.75, 118.5, 747.75]}, {"uri": "https://en.wikipedia.org/wiki/High_pressure_food_preservation", "coordinates": [86.25, 144.0, 497.25, 165.75]}, {"uri": "https://en.wikipedia.org/wiki/Pasteurization", "coordinates": [158.25, 155.25, 206.25, 165.75]}, {"uri": "https://en.wikipedia.org/w/index.php?title=Guacamole&action=edit&section=10", "coordinates": [147.0, 202.5, 159.0, 211.5]}, {"uri": "https://en.wikipedia.org/wiki/Mexican_War_of_Independence", "coordinates": [332.25, 222.0, 447.0, 232.5]}, {"uri": "https://en.wikipedia.org/w/index.php?title=Guacamole&action=edit&section=11", "coordinates": [213.0, 270.0, 225.0, 279.0]}, {"uri": "https://en.wikipedia.org/wiki/Guinness_World_Records", "coordinates": [366.75, 289.5, 470.25, 300.0]}, {"uri": "https://en.wikipedia.org/w/index.php?title=Guacamole&action=edit&section=12", "coordinates": [147.0, 348.0, 159.0, 357.0]}, {"uri": "https://en.wikipedia.org/wiki/Portal:Mexico", "coordinates": [112.5, 372.0, 166.5, 381.0]}, {"uri": "https://en.wikipedia.org/wiki/File:Foodlogo2.svg", "coordinates": [89.25, 385.5, 108.0, 394.5]}, {"uri": "https://en.wikipedia.org/wiki/Portal:Food", "coordinates": [112.5, 387.75, 157.5, 396.75]}, {"uri": "https://en.wikipedia.org/wiki/Avocado_sauce", "coordinates": [101.25, 406.5, 165.75, 417.0]}, {"uri": "https://en.wikipedia.org/wiki/List_of_avocado_dishes", "coordinates": [101.25, 418.5, 194.25, 429.0]}, {"uri": "https://en.wikipedia.org/wiki/Dipping_sauce#List_of_common_dips", "coordinates": [101.25, 430.5, 146.25, 441.0]}, {"uri": "https://en.wikipedia.org/wiki/List_of_condiments", "coordinates": [101.25, 442.5, 176.25, 453.0]}, {"uri": "https://en.wikipedia.org/wiki/List_of_Mexican_dishes", "coordinates": [101.25, 454.5, 193.5, 465.0]}, {"uri": "https://en.wikipedia.org/wiki/Mole_sauce", "coordinates": [101.25, 466.5, 149.25, 477.0]}, {"uri": "https://en.wikipedia.org/wiki/Salsa_(sauce)", "coordinates": [101.25, 478.5, 158.25, 489.0]}, {"uri": "https://en.wikipedia.org/w/index.php?title=Guacamole&action=edit&section=13", "coordinates": [167.25, 507.75, 179.25, 516.75]}, {"uri": "https://web.archive.org/web/20130901230311/http://oxforddictionaries.com/us/definition/american_english/guac", "coordinates": [120.75, 526.5, 200.25, 535.5]}, {"uri": "http://www.oxforddictionaries.com/us/definition/american_english/guac", "coordinates": [260.25, 526.5, 310.5, 535.5]}, {"uri": "https://web.archive.org/web/20180820074726/https://en.oxforddictionaries.com/definition/guac", "coordinates": [120.75, 537.0, 351.0, 546.0]}, {"uri": "https://en.oxforddictionaries.com/definition/guac", "coordinates": [132.75, 546.0, 183.0, 555.0]}, {"uri": "https://web.archive.org/web/20100323081500/http://blog.diningchicago.com/2009/11/04/eat-this-guacamole-a-singing-sauce-on-its-day/", "coordinates": [274.5, 558.0, 471.0, 567.0]}, {"uri": "http://blog.diningchicago.com/2009/11/04/eat-this-guacamole-a-singing-sauce-on-its-day/", "coordinates": [394.5, 567.75, 444.75, 576.75]}, {"uri": "https://en.wikipedia.org/wiki/James_Beard", "coordinates": [132.0, 589.5, 183.0, 598.5]}, {"uri": "https://books.google.com/books?id=s9Q7PTP-GdgC&pg=PA86", "coordinates": [114.0, 589.5, 502.5, 608.25]}, {"uri": "https://en.wikipedia.org/wiki/ISBN_(identifier)", "coordinates": [447.75, 599.25, 465.75, 608.25]}, {"uri": "https://en.wikipedia.org/wiki/Special:BookSources/978-1-59691-446-9", "coordinates": [114.0, 599.25, 493.5, 618.0]}, {"uri": "https://books.google.com/books?id=AoWlCmNDA3QC&pg=PT171", "coordinates": [245.25, 618.75, 444.75, 627.75]}, {"uri": "https://en.wikipedia.org/wiki/ISBN_(identifier)", "coordinates": [231.75, 628.5, 249.75, 637.5]}, {"uri": "https://en.wikipedia.org/wiki/Special:BookSources/978-0-19-530796-2", "coordinates": [252.0, 628.5, 326.25, 637.5]}, {"uri": "https://www.thoughtco.com/is-the-g-in-guacamole-silent-3079533", "coordinates": [120.75, 639.0, 297.75, 648.0]}, {"uri": "https://books.google.com/books?id=6ilbDwAAQBAJ&pg=PT55", "coordinates": [239.25, 648.75, 414.75, 657.75]}, {"uri": "https://en.wikipedia.org/wiki/ISBN_(identifier)", "coordinates": [228.75, 658.5, 246.75, 667.5]}, {"uri": "https://en.wikipedia.org/wiki/Special:BookSources/9781595348500", "coordinates": [249.0, 658.5, 311.25, 667.5]}, {"uri": "https://books.google.com/books?id=lKuajvrBhzsC&pg=PA241", "coordinates": [114.0, 669.0, 480.0, 687.75]}, {"uri": "https://en.wikipedia.org/wiki/ISBN_(identifier)", "coordinates": [331.5, 678.75, 349.5, 687.75]}, {"uri": "https://en.wikipedia.org/wiki/Special:BookSources/9789702604938", "coordinates": [351.75, 678.75, 414.0, 687.75]}, {"uri": "https://web.archive.org/web/20131003032429/http://oxforddictionaries.com/definition/american_english/guacamole", "coordinates": [120.75, 688.5, 420.75, 697.5]}, {"uri": "http://oxforddictionaries.com/definition/american_english/guacamole", "coordinates": [114.0, 688.5, 492.75, 707.25]}, {"uri": "https://web.archive.org/web/20120712103302/http://oxforddictionaries.com/definition/english/guacamole", "coordinates": [120.75, 708.75, 348.75, 717.75]}, {"uri": "http://www.oxforddictionaries.com/definition/english/guacamole", "coordinates": [132.75, 717.75, 183.0, 726.75]}, {"uri": "http://lifebyyou.com/us/detroit/food/guac/rock-your-guac-2018.html", "coordinates": [120.75, 728.25, 174.0, 737.25]}, {"uri": "http://ucavo.ucr.edu/General/HistoryName.html", "coordinates": [120.75, 738.75, 204.75, 747.75]}]}, {"hyperlinks": [{"uri": "", "coordinates": [114.0, 144.0, 118.5, 153.0]}, {"uri": "", "coordinates": [119.25, 174.75, 123.0, 183.75]}, {"uri": "", "coordinates": [126.0, 174.75, 129.75, 183.75]}, {"uri": "", "coordinates": [114.0, 223.5, 118.5, 232.5]}, {"uri": "", "coordinates": [114.0, 252.75, 118.5, 261.75]}, {"uri": "", "coordinates": [114.0, 273.0, 118.5, 282.0]}, {"uri": "", "coordinates": [114.0, 302.25, 118.5, 311.25]}, {"uri": "", "coordinates": [114.0, 321.75, 118.5, 330.75]}, {"uri": "", "coordinates": [114.0, 332.25, 118.5, 341.25]}, {"uri": "", "coordinates": [114.0, 351.75, 118.5, 360.75]}, {"uri": "", "coordinates": [114.0, 362.25, 118.5, 371.25]}, {"uri": "", "coordinates": [114.0, 372.0, 118.5, 381.0]}, {"uri": "", "coordinates": [114.0, 392.25, 118.5, 401.25]}, {"uri": "", "coordinates": [114.0, 411.75, 118.5, 420.75]}, {"uri": "", "coordinates": [114.0, 422.25, 118.5, 431.25]}, {"uri": "", "coordinates": [114.0, 451.5, 118.5, 460.5]}, {"uri": "", "coordinates": [114.0, 471.0, 118.5, 480.0]}, {"uri": "", "coordinates": [114.0, 491.25, 118.5, 500.25]}, {"uri": "", "coordinates": [114.0, 510.75, 118.5, 519.75]}, {"uri": "", "coordinates": [114.0, 532.5, 118.5, 541.5]}, {"uri": "", "coordinates": [114.0, 552.0, 118.5, 561.0]}, {"uri": "", "coordinates": [114.0, 572.25, 118.5, 581.25]}, {"uri": "", "coordinates": [114.0, 582.0, 118.5, 591.0]}, {"uri": "", "coordinates": [114.0, 592.5, 118.5, 601.5]}, {"uri": "", "coordinates": [114.0, 612.75, 118.5, 621.75]}, {"uri": "https://doi.org/10.1093%252Fjhered%252Fesn068", "coordinates": [114.0, 144.0, 477.0, 162.75]}, {"uri": "https://en.wikipedia.org/wiki/Doi_(identifier)", "coordinates": [114.0, 162.75, 125.25, 171.75]}, {"uri": "https://doi.org/10.1093%252Fjhered%252Fesn068", "coordinates": [127.5, 162.75, 223.5, 171.75]}, {"uri": "https://en.wikipedia.org/wiki/PMID_(identifier)", "coordinates": [228.75, 162.75, 248.25, 171.75]}, {"uri": "https://pubmed.ncbi.nlm.nih.gov/18779226", "coordinates": [251.25, 162.75, 297.75, 171.75]}, {"uri": "http://www.uv.mx/personal/megalindo/files/2010/07/GalindoTovar_325_334_V21.pdf", "coordinates": [114.0, 180.0, 489.0, 208.5]}, {"uri": "https://en.wikipedia.org/wiki/Doi_(identifier)", "coordinates": [424.5, 194.25, 435.75, 203.25]}, {"uri": "https://doi.org/10.3100%252F1043-4534%25282007%252912%255B325%253ATAPALC%255D2.0.CO%253B2", "coordinates": [114.0, 194.25, 494.25, 213.0]}, {"uri": "https://en.wikipedia.org/wiki/JSTOR_(identifier)", "coordinates": [269.25, 204.0, 296.25, 213.0]}, {"uri": "https://www.jstor.org/stable/41761865", "coordinates": [298.5, 204.0, 345.0, 213.0]}, {"uri": "https://en.wikipedia.org/wiki/S2CID_(identifier)", "coordinates": [350.25, 204.0, 374.25, 213.0]}, {"uri": "https://api.semanticscholar.org/CorpusID:9998040", "coordinates": [376.5, 204.0, 418.5, 213.0]}, {"uri": "https://web.archive.org/web/20151010145152/http://www.uv.mx/personal/megalindo/files/2010/07/GalindoTovar_325_334_V21.pdf", "coordinates": [423.0, 198.75, 466.5, 217.5]}, {"uri": "https://hort.purdue.edu/newcrop/morton/avocado_ars.html", "coordinates": [191.25, 223.5, 339.75, 232.5]}, {"uri": "https://en.wikipedia.org/wiki/ISBN_(identifier)", "coordinates": [357.0, 243.0, 375.0, 252.0]}, {"uri": "https://en.wikipedia.org/wiki/Special:BookSources/978-0-9610184-1-2", "coordinates": [378.0, 243.0, 452.25, 252.0]}, {"uri": "https://www.atlasobscura.com/articles/first-food-writer", "coordinates": [114.0, 252.75, 471.0, 271.5]}, {"uri": "https://en.wikipedia.org/wiki/Atlas_Obscura", "coordinates": [156.0, 262.5, 209.25, 271.5]}, {"uri": "https://books.google.com/books?id=p9wPoDHQR-IC", "coordinates": [114.0, 273.0, 502.5, 291.75]}, {"uri": "https://en.wikipedia.org/wiki/ISBN_(identifier)", "coordinates": [248.25, 291.75, 266.25, 300.75]}, {"uri": "https://en.wikipedia.org/wiki/Special:BookSources/978-0-415-93077-2", "coordinates": [268.5, 291.75, 342.75, 300.75]}, {"uri": "https://www.theatlantic.com/health/archive/2015/01/the-selling-of-the-avocado/385047/", "coordinates": [229.5, 302.25, 345.75, 311.25]}, {"uri": "https://www.businessinsider.com/best-guacamole-recipe-2017-5", "coordinates": [120.75, 321.75, 237.75, 330.75]}, {"uri": "https://www.seriouseats.com/2012/01/the-food-lab-the-best-guacamole-avocados-science-browning-ripening.html", "coordinates": [176.25, 332.25, 449.25, 341.25]}, {"uri": "http://cooking.nytimes.com/recipes/1015047-green-pea-guacamole?smid=tw-nytimes", "coordinates": [120.75, 351.75, 222.0, 360.75]}, {"uri": "https://web.archive.org/web/20170517130417/https://www.avocadocentral.com/avocado-recipes/avocado-party-tips-decor/national-guacamole-day-recipes-entertaining", "coordinates": [120.75, 372.0, 295.5, 381.0]}, {"uri": "https://www.avocadocentral.com/avocado-recipes/avocado-party-tips-decor/national-guacamole-day-recipes-entertaining", "coordinates": [435.75, 372.0, 486.0, 381.0]}, {"uri": "http://nutritiondata.self.com/facts/fruits-and-fruit-juices/1843/2", "coordinates": [120.75, 392.25, 342.75, 401.25]}, {"uri": "http://www.medicalnewstoday.com/articles/270406.php", "coordinates": [120.75, 411.75, 321.0, 420.75]}, {"uri": "https://www.ncbi.nlm.nih.gov/pmc/articles/PMC3664913", "coordinates": [249.0, 422.25, 468.75, 431.25]}, {"uri": "https://en.wikipedia.org/wiki/Doi_(identifier)", "coordinates": [231.75, 432.0, 243.0, 441.0]}, {"uri": "https://doi.org/10.1080%252F10408398.2011.556759", "coordinates": [246.0, 432.0, 378.75, 441.0]}, {"uri": "https://en.wikipedia.org/wiki/PMC_(identifier)", "coordinates": [384.0, 432.0, 402.0, 441.0]}, {"uri": "https://www.ncbi.nlm.nih.gov/pmc/articles/PMC3664913", "coordinates": [404.25, 432.0, 446.25, 441.0]}, {"uri": "https://en.wikipedia.org/wiki/PMID_(identifier)", "coordinates": [114.0, 441.0, 133.5, 450.0]}, {"uri": "https://pubmed.ncbi.nlm.nih.gov/23638933", "coordinates": [135.75, 441.0, 182.25, 450.0]}, {"uri": "https://books.google.com/books?id=XFYaAQAAMAAJ", "coordinates": [120.75, 451.5, 192.75, 460.5]}, {"uri": "https://web.archive.org/web/20150610201611/http://www.nypress.com/article-9759-caracas-calling.html", "coordinates": [120.75, 471.0, 195.0, 480.0]}, {"uri": "https://en.wikipedia.org/wiki/New_York_Press", "coordinates": [200.25, 471.0, 260.25, 480.0]}, {"uri": "http://www.nypress.com/article-9759-caracas-calling.html", "coordinates": [375.0, 471.0, 425.25, 480.0]}, {"uri": "https://web.archive.org/web/20131113180342/http://southamericanfood.about.com/b/2009/07/02/guasacaca-venezuelan-style-guacamole.htm", "coordinates": [120.75, 491.25, 297.75, 500.25]}, {"uri": "https://en.wikipedia.org/wiki/About.com", "coordinates": [303.0, 491.25, 342.75, 500.25]}, {"uri": "http://southamericanfood.about.com/b/2009/07/02/guasacaca-venezuelan-style-guacamole.htm", "coordinates": [453.0, 491.25, 503.25, 500.25]}, {"uri": "http://www.avocadosource.com/CAS_Yearbooks/CAS_52_1968/CAS_1968_PG_153-168.pdf", "coordinates": [203.25, 506.25, 333.75, 525.0]}, {"uri": "https://en.wikipedia.org/wiki/ISSN_(identifier)", "coordinates": [208.5, 520.5, 226.5, 529.5]}, {"uri": "https://www.worldcat.org/issn/0096-5960", "coordinates": [228.75, 520.5, 278.25, 529.5]}, {"uri": "http://www.oxforddictionaries.com/us/translate/spanish-english/guasacaca", "coordinates": [120.75, 532.5, 176.25, 541.5]}, {"uri": "https://en.wikipedia.org/wiki/Wikipedia:Link_rot", "coordinates": [424.5, 530.25, 454.5, 539.25]}, {"uri": "https://www.npr.org/2019/07/19/743599313/why-taquerias-are-making-guacamole-without-avocados", "coordinates": [232.5, 552.0, 465.75, 561.0]}, {"uri": "http://www.thepacker.com/fruit-vegetable-news/marketing-profiles/High-pressure-processing-ideal-for-guacamole-lovers-127760608.html", "coordinates": [120.75, 572.25, 333.75, 581.25]}, {"uri": "http://www.cbc.ca/kidscbc2/the-feed/national-guacamole-day", "coordinates": [120.75, 582.0, 228.75, 591.0]}, {"uri": "https://www.azcentral.com/story/sponsor-story/macayos-restaurants/2016/09/15/macayos-celebrating-mexican-independence-day-guacamole/90416352/", "coordinates": [120.75, 592.5, 384.0, 601.5]}, {"uri": "http://www.guinnessworldrecords.com/world-records/largest-serving-of-guacamole/", "coordinates": [120.75, 612.75, 246.75, 621.75]}, {"uri": "https://en.wikipedia.org/w/index.php?title=Guacamole&action=edit&section=14", "coordinates": [168.0, 636.75, 180.0, 645.75]}, {"uri": "https://en.wikipedia.org/wiki/ISBN_(identifier)", "coordinates": [293.25, 663.75, 314.25, 674.25]}, {"uri": "https://en.wikipedia.org/wiki/Special:BookSources/0387758453", "coordinates": [317.25, 663.75, 371.25, 674.25]}, {"uri": "https://en.wikipedia.org/w/index.php?title=Guacamole&action=edit&section=15", "coordinates": [185.25, 693.0, 197.25, 702.0]}, {"uri": "https://en.wikipedia.org/wiki/File:Commons-logo.svg", "coordinates": [101.25, 711.75, 108.0, 722.25]}, {"uri": "https://commons.wikimedia.org/wiki/Category:Guacamole", "coordinates": [180.75, 711.75, 228.75, 722.25]}, {"uri": "https://en.wikipedia.org/wiki/Template:Avocados", "coordinates": [96.75, 738.0, 100.5, 747.0]}, {"uri": "https://en.wikipedia.org/wiki/Template_talk:Avocados", "coordinates": [108.0, 738.0, 110.25, 747.0]}, {"uri": "https://en.wikipedia.org/wiki/Special:EditPage/Template:Avocados", "coordinates": [117.0, 738.0, 121.5, 747.0]}, {"uri": "https://en.wikipedia.org/wiki/Avocado", "coordinates": [273.75, 737.25, 319.5, 748.5]}]}, {"hyperlinks": [{"uri": "https://en.wikipedia.org/wiki/List_of_avocado_dishes", "coordinates": [96.75, 153.0, 159.0, 162.0]}, {"uri": "https://en.wikipedia.org/wiki/Avocado_oil", "coordinates": [171.0, 147.0, 214.5, 156.0]}, {"uri": "https://en.wikipedia.org/wiki/Avocado_sauce", "coordinates": [222.0, 147.0, 279.75, 156.0]}, {"uri": "https://en.wikipedia.org/wiki/Avocado_soup", "coordinates": [288.0, 147.0, 342.0, 156.0]}, {"uri": "https://en.wikipedia.org/wiki/Avocado_toast", "coordinates": [350.25, 147.0, 404.25, 156.0]}, {"uri": "https://en.wikipedia.org/wiki/Deep-fried_avocado", "coordinates": [411.75, 147.0, 486.75, 156.0]}, {"uri": "https://en.wikipedia.org/wiki/F%25C3%25A9roce", "coordinates": [171.0, 159.0, 198.0, 168.0]}, {"uri": "https://en.wikipedia.org/wiki/Sushi#Western-style_sushi", "coordinates": [260.25, 159.0, 334.5, 168.0]}, {"uri": "https://en.wikipedia.org/wiki/California_roll", "coordinates": [339.75, 159.0, 389.25, 168.0]}, {"uri": "https://en.wikipedia.org/wiki/Rainbow_roll", "coordinates": [397.5, 159.0, 443.25, 168.0]}, {"uri": "https://en.wikipedia.org/wiki/Seattle_roll", "coordinates": [451.5, 159.0, 491.25, 168.0]}, {"uri": "https://en.wikipedia.org/wiki/List_of_avocado_diseases", "coordinates": [171.0, 174.0, 205.5, 183.0]}, {"uri": "https://en.wikipedia.org/wiki/List_of_avocado_cultivars", "coordinates": [213.0, 174.0, 246.0, 183.0]}, {"uri": "https://en.wikipedia.org/wiki/Brogden_(avocado)", "coordinates": [252.0, 174.0, 284.25, 183.0]}, {"uri": "https://en.wikipedia.org/wiki/Choquette_(avocado)", "coordinates": [291.75, 174.0, 330.75, 183.0]}, {"uri": "https://en.wikipedia.org/wiki/Hass_avocado", "coordinates": [339.0, 174.0, 357.0, 183.0]}, {"uri": "https://en.wikipedia.org/wiki/Lula_(avocado)", "coordinates": [366.0, 174.0, 381.75, 183.0]}, {"uri": "https://en.wikipedia.org/wiki/Maluma_(avocado)", "coordinates": [390.0, 174.0, 419.25, 183.0]}, {"uri": "https://en.wikipedia.org/wiki/Monroe_(avocado)", "coordinates": [426.75, 174.0, 455.25, 183.0]}, {"uri": "https://en.wikipedia.org/wiki/Avocado_cultivation_by_location", "coordinates": [171.0, 186.75, 212.25, 195.75]}, {"uri": "https://en.wikipedia.org/wiki/Avocado_production_in_Mexico", "coordinates": [217.5, 186.75, 243.0, 195.75]}, {"uri": "https://en.wikipedia.org/wiki/List_of_countries_by_avocado_production", "coordinates": [251.25, 186.75, 264.0, 195.75]}, {"uri": "https://en.wikipedia.org/wiki/AvoDerm", "coordinates": [171.0, 203.25, 205.5, 212.25]}, {"uri": "https://en.wikipedia.org/wiki/California_Avocado_Commission", "coordinates": [213.0, 203.25, 332.25, 212.25]}, {"uri": "https://en.wikipedia.org/wiki/California_Avocado_Society", "coordinates": [340.5, 203.25, 441.75, 212.25]}, {"uri": "https://en.wikipedia.org/wiki/Category:Avocado", "coordinates": [246.0, 221.25, 279.0, 230.25]}, {"uri": "https://en.wikipedia.org/wiki/Category:Avocado_dishes", "coordinates": [299.25, 221.25, 359.25, 230.25]}, {"uri": "https://en.wikipedia.org/wiki/Template:Condiments", "coordinates": [96.75, 242.25, 100.5, 251.25]}, {"uri": "https://en.wikipedia.org/wiki/Template_talk:Condiments", "coordinates": [108.0, 242.25, 110.25, 251.25]}, {"uri": "https://en.wikipedia.org/wiki/Special:EditPage/Template:Condiments", "coordinates": [117.0, 242.25, 121.5, 251.25]}, {"uri": "https://en.wikipedia.org/wiki/Condiment", "coordinates": [269.25, 241.5, 324.75, 252.75]}, {"uri": "https://en.wikipedia.org/wiki/List_of_condiments", "coordinates": [192.0, 260.25, 260.25, 269.25]}, {"uri": "https://en.wikipedia.org/wiki/Dip_(food)#List_of_common_dips", "coordinates": [268.5, 260.25, 343.5, 269.25]}, {"uri": "https://en.wikipedia.org/wiki/List_of_syrups", "coordinates": [351.0, 260.25, 401.25, 269.25]}, {"uri": "https://en.wikipedia.org/wiki/Agre_dulce", "coordinates": [193.5, 276.75, 234.0, 285.75]}, {"uri": "https://en.wikipedia.org/wiki/Agrodolce", "coordinates": [242.25, 276.75, 280.5, 285.75]}, {"uri": "https://en.wikipedia.org/wiki/Aioli", "coordinates": [288.0, 276.75, 303.0, 285.75]}, {"uri": "https://en.wikipedia.org/wiki/Barbecue_sauce", "coordinates": [312.0, 276.75, 373.5, 285.75]}, {"uri": "https://en.wikipedia.org/wiki/Bigarade_sauce", "coordinates": [193.5, 289.5, 252.75, 298.5]}, {"uri": "https://en.wikipedia.org/wiki/Brown_sauce", "coordinates": [261.0, 289.5, 309.0, 298.5]}, {"uri": "https://en.wikipedia.org/wiki/Buffalo_sauce", "coordinates": [317.25, 289.5, 368.25, 298.5]}, {"uri": "https://en.wikipedia.org/wiki/Cheese_sauce", "coordinates": [193.5, 302.25, 247.5, 311.25]}, {"uri": "https://en.wikipedia.org/wiki/Alfredo_sauce", "coordinates": [253.5, 302.25, 305.25, 311.25]}, {"uri": "https://en.wikipedia.org/wiki/Caruso_sauce", "coordinates": [313.5, 302.25, 366.0, 311.25]}, {"uri": "https://en.wikipedia.org/wiki/Cheddar_sauce", "coordinates": [193.5, 315.0, 251.25, 324.0]}, {"uri": "https://en.wikipedia.org/wiki/Cheez_Whiz", "coordinates": [259.5, 315.0, 303.75, 324.0]}, {"uri": "https://en.wikipedia.org/wiki/Fondue", "coordinates": [312.0, 315.0, 341.25, 324.0]}, {"uri": "https://en.wikipedia.org/wiki/Mornay_sauce", "coordinates": [348.75, 315.0, 402.0, 324.0]}, {"uri": "https://en.wikipedia.org/wiki/Nacho_cheese", "coordinates": [193.5, 327.0, 247.5, 336.0]}, {"uri": "https://en.wikipedia.org/wiki/Chili_sauce_and_paste", "coordinates": [258.0, 327.0, 299.25, 336.0]}, {"uri": "https://en.wikipedia.org/wiki/Chimichurri", "coordinates": [307.5, 327.0, 349.5, 336.0]}, {"uri": "https://en.wikipedia.org/wiki/Cocktail_sauce", "coordinates": [357.75, 327.0, 412.5, 336.0]}, {"uri": "https://en.wikipedia.org/wiki/Colo-colo_(condiment)", "coordinates": [193.5, 339.75, 229.5, 348.75]}, {"uri": "https://en.wikipedia.org/wiki/Crema_(dairy_product)", "coordinates": [237.0, 339.75, 261.75, 348.75]}, {"uri": "https://en.wikipedia.org/wiki/Caruru_(food)", "coordinates": [270.0, 339.75, 296.25, 348.75]}, {"uri": "https://en.wikipedia.org/wiki/Dabu-dabu", "coordinates": [304.5, 339.75, 346.5, 348.75]}, {"uri": "https://en.wikipedia.org/wiki/Fish_sauce", "coordinates": [354.75, 339.75, 396.0, 348.75]}, {"uri": "https://en.wikipedia.org/wiki/Fritessaus", "coordinates": [193.5, 352.5, 232.5, 361.5]}, {"uri": "https://en.wikipedia.org/wiki/Fry_sauce", "coordinates": [240.75, 352.5, 278.25, 361.5]}, {"uri": "https://en.wikipedia.org/wiki/Garum", "coordinates": [286.5, 352.5, 312.0, 361.5]}, {"uri": "https://en.wikipedia.org/wiki/Gastrique", "coordinates": [320.25, 352.5, 357.0, 361.5]}, {"uri": "https://en.wikipedia.org/wiki/Gravy", "coordinates": [365.25, 352.5, 387.75, 361.5]}, {"uri": "https://en.wikipedia.org/wiki/Hot_sauce", "coordinates": [193.5, 365.25, 231.0, 374.25]}, {"uri": "https://en.wikipedia.org/wiki/Latik", "coordinates": [239.25, 365.25, 257.25, 374.25]}, {"uri": "https://en.wikipedia.org/wiki/Kaymak", "coordinates": [264.75, 365.25, 294.75, 374.25]}, {"uri": "https://en.wikipedia.org/wiki/Khrenovina_sauce", "coordinates": [303.0, 365.25, 345.75, 374.25]}, {"uri": "https://en.wikipedia.org/wiki/Lechon_sauce", "coordinates": [354.0, 365.25, 407.25, 374.25]}, {"uri": "https://en.wikipedia.org/wiki/Marie_Rose_sauce", "coordinates": [193.5, 378.0, 261.75, 387.0]}, {"uri": "https://en.wikipedia.org/wiki/Mayonnaise", "coordinates": [270.0, 378.0, 315.0, 387.0]}, {"uri": "https://en.wikipedia.org/wiki/Kewpie_(mayonnaise)", "coordinates": [321.0, 378.0, 348.0, 387.0]}, {"uri": "https://en.wikipedia.org/wiki/Kielecki_Mayonnaise", "coordinates": [355.5, 378.0, 384.0, 387.0]}, {"uri": "https://en.wikipedia.org/wiki/Miracle_Whip", "coordinates": [193.5, 390.0, 241.5, 399.0]}, {"uri": "https://en.wikipedia.org/wiki/Mignonette_sauce", "coordinates": [252.75, 390.0, 319.5, 399.0]}, {"uri": "https://en.wikipedia.org/wiki/Mild_sauce", "coordinates": [327.75, 390.0, 367.5, 399.0]}, {"uri": "https://en.wikipedia.org/wiki/Monkey_gland_sauce", "coordinates": [193.5, 402.75, 271.5, 411.75]}, {"uri": "https://en.wikipedia.org/wiki/Mumbo_sauce", "coordinates": [279.0, 402.75, 331.5, 411.75]}, {"uri": "https://en.wikipedia.org/wiki/Oyster_sauce", "coordinates": [339.75, 402.75, 390.0, 411.75]}, {"uri": "https://en.wikipedia.org/wiki/Peanut_sauce", "coordinates": [193.5, 415.5, 245.25, 424.5]}, {"uri": "https://en.wikipedia.org/wiki/Pear%25C3%25A0", "coordinates": [253.5, 415.5, 276.0, 424.5]}, {"uri": "https://en.wikipedia.org/wiki/Pesto", "coordinates": [284.25, 415.5, 305.25, 424.5]}, {"uri": "https://en.wikipedia.org/wiki/Pistou", "coordinates": [313.5, 415.5, 336.75, 424.5]}, {"uri": "https://en.wikipedia.org/wiki/Remoulade", "coordinates": [345.0, 415.5, 387.75, 424.5]}, {"uri": "https://en.wikipedia.org/wiki/Salsa_roja", "coordinates": [193.5, 428.25, 231.0, 437.25]}, {"uri": "https://en.wikipedia.org/wiki/Salsa_golf", "coordinates": [239.25, 428.25, 276.0, 437.25]}, {"uri": "https://en.wikipedia.org/wiki/Salsa_verde", "coordinates": [284.25, 428.25, 329.25, 437.25]}, {"uri": "https://en.wikipedia.org/wiki/Satsivi", "coordinates": [336.75, 428.25, 360.75, 437.25]}, {"uri": "https://en.wikipedia.org/wiki/Steak_sauce", "coordinates": [369.0, 428.25, 415.5, 437.25]}, {"uri": "https://en.wikipedia.org/wiki/Tartar_sauce", "coordinates": [193.5, 441.0, 241.5, 450.0]}, {"uri": "https://en.wikipedia.org/wiki/Tatbila", "coordinates": [249.75, 441.0, 275.25, 450.0]}, {"uri": "https://en.wikipedia.org/wiki/Teriyaki", "coordinates": [283.5, 441.0, 338.25, 450.0]}, {"uri": "https://en.wikipedia.org/wiki/Tiparos", "coordinates": [346.5, 441.0, 375.0, 450.0]}, {"uri": "https://en.wikipedia.org/wiki/Tkemali", "coordinates": [383.25, 441.0, 412.5, 450.0]}, {"uri": "https://en.wikipedia.org/wiki/Tomato_sauce", "coordinates": [193.5, 453.0, 247.5, 462.0]}, {"uri": "https://en.wikipedia.org/wiki/Vincotto", "coordinates": [255.0, 453.0, 285.0, 462.0]}, {"uri": "https://en.wikipedia.org/wiki/XO_sauce", "coordinates": [294.0, 453.0, 330.0, 462.0]}, {"uri": "https://en.wikipedia.org/wiki/%25C3%2580_la_zingara", "coordinates": [338.25, 453.0, 392.25, 462.0]}, {"uri": "https://en.wikipedia.org/wiki/File:Different_ketchup_in_a_plate_122425.jpg", "coordinates": [429.0, 689.25, 505.5, 698.25]}, {"uri": "https://en.wikipedia.org/wiki/Dipping_sauce", "coordinates": [163.5, 493.5, 181.5, 502.5]}, {"uri": "https://en.wikipedia.org/wiki/Ajika", "coordinates": [193.5, 468.0, 211.5, 477.0]}, {"uri": "https://en.wikipedia.org/wiki/Baba_ghanoush", "coordinates": [219.0, 468.0, 279.0, 477.0]}, {"uri": "https://en.wikipedia.org/wiki/Chile_con_queso", "coordinates": [287.25, 468.0, 348.0, 477.0]}, {"uri": "https://en.wikipedia.org/wiki/Duck_sauce", "coordinates": [356.25, 468.0, 400.5, 477.0]}, {"uri": "https://en.wikipedia.org/wiki/Duqqa", "coordinates": [193.5, 480.75, 218.25, 489.75]}, {"uri": "https://en.wikipedia.org/wiki/Garlic_chive_flower_sauce", "coordinates": [226.5, 480.75, 320.25, 489.75]}, {"uri": "https://en.wikipedia.org/wiki/Hogao", "coordinates": [383.25, 480.75, 407.25, 489.75]}, {"uri": "https://en.wikipedia.org/wiki/Honey_dill", "coordinates": [193.5, 493.5, 229.5, 502.5]}, {"uri": "https://en.wikipedia.org/wiki/Hummus", "coordinates": [237.75, 493.5, 270.0, 502.5]}, {"uri": "https://en.wikipedia.org/wiki/Muhammara", "coordinates": [278.25, 493.5, 324.75, 502.5]}, {"uri": "https://en.wikipedia.org/wiki/Nam_chim", "coordinates": [333.0, 493.5, 369.0, 502.5]}, {"uri": "https://en.wikipedia.org/wiki/Nam_phrik", "coordinates": [377.25, 493.5, 414.75, 502.5]}, {"uri": "https://en.wikipedia.org/wiki/N%25C6%25B0%25E1%25BB%259Bc_ch%25E1%25BA%25A5m", "coordinates": [193.5, 506.25, 236.25, 515.25]}, {"uri": "https://en.wikipedia.org/wiki/Skyronnes", "coordinates": [244.5, 506.25, 284.25, 515.25]}, {"uri": "https://en.wikipedia.org/wiki/Sweet_chili_sauce", "coordinates": [292.5, 506.25, 357.0, 515.25]}, {"uri": "https://en.wikipedia.org/wiki/Toum", "coordinates": [365.25, 506.25, 386.25, 515.25]}, {"uri": "https://en.wikipedia.org/wiki/Tzatziki", "coordinates": [394.5, 506.25, 421.5, 515.25]}, {"uri": "https://en.wikipedia.org/wiki/Zhug", "coordinates": [198.75, 519.0, 217.5, 528.0]}, {"uri": "https://en.wikipedia.org/wiki/Amba_(condiment)", "coordinates": [193.5, 534.0, 214.5, 543.0]}, {"uri": "https://en.wikipedia.org/wiki/Atchara", "coordinates": [222.75, 534.0, 252.0, 543.0]}, {"uri": "https://en.wikipedia.org/wiki/Cheong_(food)", "coordinates": [260.25, 534.0, 290.25, 543.0]}, {"uri": "https://en.wikipedia.org/wiki/Chutney", "coordinates": [297.75, 534.0, 329.25, 543.0]}, {"uri": "https://en.wikipedia.org/wiki/Green_mango_chutney", "coordinates": [335.25, 534.0, 419.25, 543.0]}, {"uri": "https://en.wikipedia.org/wiki/Curtido", "coordinates": [198.75, 546.0, 225.75, 555.0]}, {"uri": "https://en.wikipedia.org/wiki/Encurtido", "coordinates": [234.0, 546.0, 270.0, 555.0]}, {"uri": "https://en.wikipedia.org/wiki/Fruit_preserves", "coordinates": [278.25, 546.0, 335.25, 555.0]}, {"uri": "https://en.wikipedia.org/wiki/Gari_(ginger)", "coordinates": [343.5, 546.0, 359.25, 555.0]}, {"uri": "https://en.wikipedia.org/wiki/Horseradish", "coordinates": [367.5, 546.0, 412.5, 555.0]}, {"uri": "https://en.wikipedia.org/wiki/Ljutenica", "coordinates": [193.5, 558.75, 227.25, 567.75]}, {"uri": "https://en.wikipedia.org/wiki/Pepper_jelly", "coordinates": [235.5, 558.75, 279.75, 567.75]}, {"uri": "https://en.wikipedia.org/wiki/Piccalilli", "coordinates": [288.0, 558.75, 317.25, 567.75]}, {"uri": "https://en.wikipedia.org/wiki/Pickled_cucumber", "coordinates": [324.75, 558.75, 390.75, 567.75]}, {"uri": "https://en.wikipedia.org/wiki/Pickled_fruit", "coordinates": [193.5, 571.5, 237.0, 580.5]}, {"uri": "https://en.wikipedia.org/wiki/Relish", "coordinates": [245.25, 571.5, 268.5, 580.5]}, {"uri": "https://en.wikipedia.org/wiki/Chicago-style_relish", "coordinates": [273.75, 571.5, 348.0, 580.5]}, {"uri": "https://en.wikipedia.org/wiki/Sauerkraut", "coordinates": [359.25, 571.5, 401.25, 580.5]}, {"uri": "https://en.wikipedia.org/wiki/Sumbala", "coordinates": [193.5, 584.25, 226.5, 593.25]}, {"uri": "https://en.wikipedia.org/wiki/Taba_ng_talangka", "coordinates": [234.0, 584.25, 300.0, 593.25]}, {"uri": "https://en.wikipedia.org/wiki/Tomato_jam", "coordinates": [309.0, 584.25, 353.25, 593.25]}, {"uri": "https://en.wikipedia.org/wiki/Watermelon_rind_preserves", "coordinates": [193.5, 597.0, 295.5, 606.0]}, {"uri": "https://en.wikipedia.org/wiki/Ajvar", "coordinates": [193.5, 612.0, 212.25, 621.0]}, {"uri": "https://en.wikipedia.org/wiki/Anchovy_paste", "coordinates": [220.5, 612.0, 276.0, 621.0]}, {"uri": "https://en.wikipedia.org/wiki/Bagoong", "coordinates": [284.25, 612.0, 318.0, 621.0]}, {"uri": "https://en.wikipedia.org/wiki/Sal%25C3%25A7a", "coordinates": [326.25, 612.0, 374.25, 621.0]}, {"uri": "https://en.wikipedia.org/wiki/Beurre_Ma%25C3%25AEtre_d%2527H%25C3%25B4tel", "coordinates": [193.5, 624.75, 273.75, 633.75]}, {"uri": "https://en.wikipedia.org/wiki/Chili_paste", "coordinates": [282.0, 624.75, 321.0, 633.75]}, {"uri": "https://en.wikipedia.org/wiki/Chrain", "coordinates": [329.25, 624.75, 354.0, 633.75]}, {"uri": "https://en.wikipedia.org/wiki/Coconut_jam", "coordinates": [362.25, 624.75, 409.5, 633.75]}, {"uri": "https://en.wikipedia.org/wiki/Fish_paste", "coordinates": [193.5, 636.75, 232.5, 645.75]}, {"uri": "https://en.wikipedia.org/wiki/Gochujang", "coordinates": [240.75, 636.75, 282.0, 645.75]}, {"uri": "https://en.wikipedia.org/wiki/Harif", "coordinates": [290.25, 636.75, 307.5, 645.75]}, {"uri": "https://en.wikipedia.org/wiki/Liver_spread", "coordinates": [315.0, 636.75, 362.25, 645.75]}, {"uri": "https://en.wikipedia.org/wiki/Kyopolou", "coordinates": [370.5, 636.75, 405.75, 645.75]}, {"uri": "https://en.wikipedia.org/wiki/Maafe", "coordinates": [193.5, 649.5, 216.75, 658.5]}, {"uri": "https://en.wikipedia.org/wiki/Malidzano", "coordinates": [225.0, 649.5, 262.5, 658.5]}, {"uri": "https://en.wikipedia.org/wiki/Meat_extract", "coordinates": [270.0, 649.5, 315.75, 658.5]}, {"uri": "https://en.wikipedia.org/wiki/Bovril", "coordinates": [321.75, 649.5, 342.75, 658.5]}, {"uri": "https://en.wikipedia.org/wiki/Murri_(condiment)", "coordinates": [354.0, 649.5, 372.75, 658.5]}, {"uri": "https://en.wikipedia.org/wiki/Nut_butter", "coordinates": [381.0, 649.5, 417.75, 658.5]}, {"uri": "https://en.wikipedia.org/wiki/Palapa_(condiment)", "coordinates": [193.5, 662.25, 219.75, 671.25]}, {"uri": "https://en.wikipedia.org/wiki/Pindjur", "coordinates": [228.0, 662.25, 254.25, 671.25]}, {"uri": "https://en.wikipedia.org/wiki/Roe", "coordinates": [261.75, 662.25, 276.75, 671.25]}, {"uri": "https://en.wikipedia.org/wiki/Caviar", "coordinates": [282.75, 662.25, 306.75, 671.25]}, {"uri": "https://en.wikipedia.org/wiki/Tapai", "coordinates": [318.0, 662.25, 339.0, 671.25]}, {"uri": "https://en.wikipedia.org/wiki/Wasabi", "coordinates": [348.0, 662.25, 375.75, 671.25]}, {"uri": "https://en.wikipedia.org/wiki/Yeast_extract", "coordinates": [193.5, 675.0, 242.25, 684.0]}, {"uri": "https://en.wikipedia.org/wiki/Marmite", "coordinates": [248.25, 675.0, 278.25, 684.0]}, {"uri": "https://en.wikipedia.org/wiki/Vegemite", "coordinates": [285.75, 675.0, 321.0, 684.0]}, {"uri": "https://en.wikipedia.org/wiki/Zacusc%25C4%2583", "coordinates": [332.25, 675.0, 363.75, 684.0]}, {"uri": "https://en.wikipedia.org/wiki/Chili_oil", "coordinates": [193.5, 690.0, 220.5, 699.0]}, {"uri": "https://en.wikipedia.org/wiki/Halford_Leicestershire_Table_Sauce", "coordinates": [228.0, 690.0, 360.75, 699.0]}, {"uri": "https://en.wikipedia.org/wiki/Mustard_oil", "coordinates": [369.0, 690.0, 410.25, 699.0]}, {"uri": "https://en.wikipedia.org/wiki/Olive_oil", "coordinates": [193.5, 702.75, 223.5, 711.75]}, {"uri": "https://en.wikipedia.org/wiki/Patis_(sauce)", "coordinates": [231.0, 702.75, 249.0, 711.75]}, {"uri": "https://en.wikipedia.org/wiki/Perilla_oil", "coordinates": [258.0, 702.75, 291.75, 711.75]}, {"uri": "https://en.wikipedia.org/wiki/Ponzu", "coordinates": [300.0, 702.75, 323.25, 711.75]}, {"uri": "https://en.wikipedia.org/wiki/Salmoriglio", "coordinates": [330.75, 702.75, 372.0, 711.75]}, {"uri": "https://en.wikipedia.org/wiki/Sesame_oil", "coordinates": [380.25, 702.75, 421.5, 711.75]}, {"uri": "https://en.wikipedia.org/wiki/Soy_sauce", "coordinates": [198.75, 714.75, 237.75, 723.75]}, {"uri": "https://en.wikipedia.org/wiki/Soup_soy_sauce", "coordinates": [243.75, 714.75, 303.75, 723.75]}, {"uri": "https://en.wikipedia.org/wiki/Sweet_soy_sauce", "coordinates": [312.0, 714.75, 375.0, 723.75]}, {"uri": "https://en.wikipedia.org/wiki/Toyomansi", "coordinates": [193.5, 727.5, 234.75, 736.5]}, {"uri": "https://en.wikipedia.org/wiki/Syrup", "coordinates": [246.0, 727.5, 267.75, 736.5]}, {"uri": "https://en.wikipedia.org/wiki/Worcestershire_sauce", "coordinates": [276.0, 727.5, 358.5, 736.5]}, {"uri": "https://en.wikipedia.org/wiki/Tonkatsu_sauce", "coordinates": [196.5, 740.25, 256.5, 749.25]}]}, {"hyperlinks": [{"uri": "https://en.wikipedia.org/wiki/As%25C3%25ADn_tibuok", "coordinates": [193.5, 147.0, 235.5, 156.0]}, {"uri": "https://en.wikipedia.org/wiki/Chipotle", "coordinates": [243.0, 147.0, 273.75, 156.0]}, {"uri": "https://en.wikipedia.org/wiki/Crushed_red_pepper", "coordinates": [282.0, 147.0, 358.5, 156.0]}, {"uri": "https://en.wikipedia.org/wiki/Gomashio", "coordinates": [366.75, 147.0, 405.0, 156.0]}, {"uri": "https://en.wikipedia.org/wiki/MSG", "coordinates": [193.5, 159.0, 211.5, 168.0]}, {"uri": "https://en.wikipedia.org/wiki/Nutritional_yeast", "coordinates": [219.75, 159.0, 279.75, 168.0]}, {"uri": "https://en.wikipedia.org/wiki/Paprika", "coordinates": [288.0, 159.0, 316.5, 168.0]}, {"uri": "https://en.wikipedia.org/wiki/Popcorn_seasoning", "coordinates": [324.75, 159.0, 397.5, 168.0]}, {"uri": "https://en.wikipedia.org/wiki/Salt_and_pepper", "coordinates": [193.5, 171.75, 253.5, 180.75]}, {"uri": "https://en.wikipedia.org/wiki/Tekka", "coordinates": [261.75, 171.75, 285.0, 180.75]}, {"uri": "https://en.wikipedia.org/wiki/Za%2527atar", "coordinates": [293.25, 171.75, 319.5, 180.75]}, {"uri": "https://en.wikipedia.org/wiki/Carolina_style", "coordinates": [193.5, 186.75, 244.5, 195.75]}, {"uri": "https://en.wikipedia.org/wiki/Coleslaw", "coordinates": [252.75, 186.75, 285.75, 195.75]}, {"uri": "https://en.wikipedia.org/wiki/Kachumbari", "coordinates": [294.0, 186.75, 339.0, 195.75]}, {"uri": "https://en.wikipedia.org/wiki/Kachumber", "coordinates": [347.25, 186.75, 390.0, 195.75]}, {"uri": "https://en.wikipedia.org/wiki/Salsa_(Mexican_cuisine)", "coordinates": [398.25, 186.75, 419.25, 195.75]}, {"uri": "https://en.wikipedia.org/wiki/Pico_de_gallo", "coordinates": [196.5, 199.5, 244.5, 208.5]}, {"uri": "https://en.wikipedia.org/wiki/Salsa_criolla", "coordinates": [252.75, 199.5, 297.75, 208.5]}, {"uri": "https://en.wikipedia.org/wiki/Salad_dressing", "coordinates": [139.5, 240.0, 181.5, 249.0]}, {"uri": "https://en.wikipedia.org/wiki/Blue_cheese_dressing", "coordinates": [193.5, 214.5, 274.5, 223.5]}, {"uri": "https://en.wikipedia.org/wiki/French_dressing", "coordinates": [282.75, 214.5, 344.25, 223.5]}, {"uri": "https://en.wikipedia.org/wiki/Ginger_dressing", "coordinates": [352.5, 214.5, 412.5, 223.5]}, {"uri": "https://en.wikipedia.org/wiki/Green_goddess_dressing", "coordinates": [193.5, 227.25, 286.5, 236.25]}, {"uri": "https://en.wikipedia.org/wiki/Italian_dressing", "coordinates": [294.75, 227.25, 351.75, 236.25]}, {"uri": "https://en.wikipedia.org/wiki/Louis_dressing", "coordinates": [360.0, 227.25, 414.75, 236.25]}, {"uri": "https://en.wikipedia.org/wiki/Mayfair_salad_dressing", "coordinates": [193.5, 240.0, 278.25, 249.0]}, {"uri": "https://en.wikipedia.org/wiki/Ranch_dressing", "coordinates": [286.5, 240.0, 345.75, 249.0]}, {"uri": "https://en.wikipedia.org/wiki/Russian_dressing", "coordinates": [354.0, 240.0, 419.25, 249.0]}, {"uri": "https://en.wikipedia.org/wiki/Salad_cream", "coordinates": [193.5, 252.0, 240.75, 261.0]}, {"uri": "https://en.wikipedia.org/wiki/Tahini_sauce", "coordinates": [249.0, 252.0, 272.25, 261.0]}, {"uri": "https://en.wikipedia.org/wiki/Thousand_Island_dressing", "coordinates": [279.75, 252.0, 342.75, 261.0]}, {"uri": "https://en.wikipedia.org/wiki/Vinaigrette", "coordinates": [351.0, 252.0, 391.5, 261.0]}, {"uri": "https://en.wikipedia.org/wiki/Wafu_dressing", "coordinates": [196.5, 264.75, 250.5, 273.75]}, {"uri": "https://en.wikipedia.org/wiki/Ketchup", "coordinates": [141.75, 285.75, 181.5, 294.75]}, {"uri": "https://en.wikipedia.org/wiki/Banana_ketchup", "coordinates": [193.5, 279.75, 255.0, 288.75]}, {"uri": "https://en.wikipedia.org/wiki/Curry_ketchup", "coordinates": [263.25, 279.75, 316.5, 288.75]}, {"uri": "https://en.wikipedia.org/wiki/Fruit_ketchup", "coordinates": [324.0, 279.75, 373.5, 288.75]}, {"uri": "https://en.wikipedia.org/wiki/Mushroom_ketchup", "coordinates": [193.5, 292.5, 265.5, 301.5]}, {"uri": "https://en.wikipedia.org/wiki/Mustard_(condiment)", "coordinates": [142.5, 326.25, 181.5, 335.25]}, {"uri": "https://en.wikipedia.org/wiki/Dijon_mustard", "coordinates": [193.5, 307.5, 245.25, 316.5]}, {"uri": "https://en.wikipedia.org/wiki/Honey_mustard", "coordinates": [253.5, 307.5, 310.5, 316.5]}, {"uri": "https://en.wikipedia.org/wiki/Karashi", "coordinates": [318.0, 307.5, 346.5, 316.5]}, {"uri": "https://en.wikipedia.org/wiki/Kasundi", "coordinates": [354.75, 307.5, 384.75, 316.5]}, {"uri": "https://en.wikipedia.org/wiki/Mostarda", "coordinates": [193.5, 320.25, 228.75, 329.25]}, {"uri": "https://en.wikipedia.org/wiki/Mustard_(condiment)#Spicy_brown/deli-style_mustard", "coordinates": [237.0, 320.25, 315.0, 329.25]}, {"uri": "https://en.wikipedia.org/wiki/Creole_mustard", "coordinates": [321.0, 320.25, 378.75, 329.25]}, {"uri": "https://en.wikipedia.org/wiki/Mustard_(condiment)#Sweet_mustard", "coordinates": [193.5, 333.0, 249.0, 342.0]}, {"uri": "https://en.wikipedia.org/wiki/Tecuci", "coordinates": [257.25, 333.0, 315.0, 342.0]}, {"uri": "https://en.wikipedia.org/wiki/Tewkesbury_mustard", "coordinates": [323.25, 333.0, 401.25, 342.0]}, {"uri": "https://en.wikipedia.org/wiki/Turun_sinappi", "coordinates": [193.5, 345.0, 245.25, 354.0]}, {"uri": "https://en.wikipedia.org/wiki/Mustard_(condiment)#American/yellow_mustard", "coordinates": [253.5, 345.0, 310.5, 354.0]}, {"uri": "https://en.wikipedia.org/wiki/Vinegar", "coordinates": [144.75, 372.75, 181.5, 381.75]}, {"uri": "https://en.wikipedia.org/wiki/Apple_cider_vinegar", "coordinates": [193.5, 360.0, 266.25, 369.0]}, {"uri": "https://en.wikipedia.org/wiki/Balsamic_vinegar", "coordinates": [274.5, 360.0, 338.25, 369.0]}, {"uri": "https://en.wikipedia.org/wiki/Balsamic_vinegar_of_Modena", "coordinates": [196.5, 372.75, 303.0, 381.75]}, {"uri": "https://en.wikipedia.org/wiki/Black_vinegar", "coordinates": [314.25, 372.75, 365.25, 381.75]}, {"uri": "https://en.wikipedia.org/wiki/Kaong_palm_vinegar", "coordinates": [193.5, 385.5, 268.5, 394.5]}, {"uri": "https://en.wikipedia.org/wiki/Malt_vinegar", "coordinates": [276.75, 385.5, 322.5, 394.5]}, {"uri": "https://en.wikipedia.org/wiki/Nipa_palm_vinegar", "coordinates": [330.75, 385.5, 398.25, 394.5]}, {"uri": "https://en.wikipedia.org/wiki/List_of_accompaniments_to_french_fries", "coordinates": [193.5, 400.5, 312.0, 409.5]}, {"uri": "https://en.wikipedia.org/wiki/List_of_brand_name_condiments", "coordinates": [320.25, 400.5, 411.75, 409.5]}, {"uri": "https://en.wikipedia.org/wiki/List_of_chutneys", "coordinates": [193.5, 413.25, 229.5, 422.25]}, {"uri": "https://en.wikipedia.org/wiki/Fish_paste#Traditional_pastes", "coordinates": [237.0, 413.25, 280.5, 422.25]}, {"uri": "https://en.wikipedia.org/wiki/List_of_fish_sauces", "coordinates": [288.75, 413.25, 333.75, 422.25]}, {"uri": "https://en.wikipedia.org/wiki/List_of_Indian_condiments", "coordinates": [342.0, 413.25, 410.25, 422.25]}, {"uri": "https://en.wikipedia.org/wiki/List_of_Indonesian_condiments", "coordinates": [193.5, 426.0, 280.5, 435.0]}, {"uri": "https://en.wikipedia.org/wiki/List_of_Japanese_condiments", "coordinates": [288.0, 426.0, 369.75, 435.0]}, {"uri": "https://en.wikipedia.org/wiki/List_of_mayonnaises", "coordinates": [193.5, 438.0, 243.0, 447.0]}, {"uri": "https://en.wikipedia.org/wiki/List_of_mustard_brands", "coordinates": [251.25, 438.0, 310.5, 447.0]}, {"uri": "https://en.wikipedia.org/wiki/List_of_hot_sauces", "coordinates": [318.0, 438.0, 360.0, 447.0]}, {"uri": "https://en.wikipedia.org/wiki/List_of_Pakistani_condiments", "coordinates": [193.5, 450.75, 273.0, 459.75]}, {"uri": "https://en.wikipedia.org/wiki/Philippine_condiments", "coordinates": [281.25, 450.75, 363.0, 459.75]}, {"uri": "https://en.wikipedia.org/wiki/List_of_pickled_foods", "coordinates": [371.25, 450.75, 421.5, 459.75]}, {"uri": "https://en.wikipedia.org/wiki/Cruet-stand", "coordinates": [193.5, 465.75, 238.5, 474.75]}, {"uri": "https://en.wikipedia.org/wiki/Sachet_(scented_bag)", "coordinates": [246.0, 465.75, 272.25, 474.75]}, {"uri": "https://en.wikipedia.org/wiki/Salt_and_pepper_shakers", "coordinates": [280.5, 465.75, 373.5, 474.75]}, {"uri": "https://en.wikipedia.org/wiki/Squeeze_bottle", "coordinates": [193.5, 478.5, 249.75, 487.5]}, {"uri": "https://en.wikipedia.org/wiki/Template:Mexican_cuisine", "coordinates": [96.75, 498.0, 100.5, 507.0]}, {"uri": "https://en.wikipedia.org/wiki/Template_talk:Mexican_cuisine", "coordinates": [108.0, 498.0, 110.25, 507.0]}, {"uri": "https://en.wikipedia.org/wiki/Special:EditPage/Template:Mexican_cuisine", "coordinates": [117.0, 498.0, 121.5, 507.0]}, {"uri": "https://en.wikipedia.org/wiki/Mexican_cuisine", "coordinates": [260.25, 497.25, 333.75, 508.5]}, {"uri": "https://en.wikipedia.org/wiki/List_of_Mexican_dishes", "coordinates": [249.75, 515.25, 343.5, 524.25]}, {"uri": "https://en.wikipedia.org/wiki/Birria", "coordinates": [171.0, 531.0, 190.5, 540.0]}, {"uri": "https://en.wikipedia.org/wiki/Caldo_de_pollo", "coordinates": [198.75, 531.0, 252.75, 540.0]}, {"uri": "https://en.wikipedia.org/wiki/Caldo_de_queso", "coordinates": [261.0, 531.0, 321.0, 540.0]}, {"uri": "https://en.wikipedia.org/wiki/Caldo_de_siete_mares", "coordinates": [329.25, 531.0, 409.5, 540.0]}, {"uri": "https://en.wikipedia.org/wiki/Caldo_tlalpe%25C3%25B1o", "coordinates": [171.0, 543.75, 225.0, 552.75]}, {"uri": "https://en.wikipedia.org/wiki/Caldo_X%25C3%25B3chitl", "coordinates": [234.0, 543.75, 282.75, 552.75]}, {"uri": "https://en.wikipedia.org/wiki/Chileatole", "coordinates": [291.0, 543.75, 328.5, 552.75]}, {"uri": "https://en.wikipedia.org/wiki/Clemole", "coordinates": [336.0, 543.75, 366.0, 552.75]}, {"uri": "https://en.wikipedia.org/wiki/Cocido", "coordinates": [375.0, 543.75, 401.25, 552.75]}, {"uri": "https://en.wikipedia.org/wiki/Lime_soup", "coordinates": [171.0, 556.5, 210.0, 565.5]}, {"uri": "https://en.wikipedia.org/wiki/Manchamanteles", "coordinates": [218.25, 556.5, 282.0, 565.5]}, {"uri": "https://en.wikipedia.org/wiki/Menudo_(soup)", "coordinates": [290.25, 556.5, 320.25, 565.5]}, {"uri": "https://en.wikipedia.org/wiki/Mole_de_olla", "coordinates": [328.5, 556.5, 373.5, 565.5]}, {"uri": "https://en.wikipedia.org/wiki/Pozole", "coordinates": [381.75, 556.5, 406.5, 565.5]}, {"uri": "https://en.wikipedia.org/wiki/Sopa_de_fideo", "coordinates": [171.0, 569.25, 223.5, 578.25]}, {"uri": "https://en.wikipedia.org/wiki/Nopalito", "coordinates": [231.75, 569.25, 286.5, 578.25]}, {"uri": "https://en.wikipedia.org/wiki/Tortilla_soup", "coordinates": [294.75, 569.25, 341.25, 578.25]}, {"uri": "https://en.wikipedia.org/wiki/File:SopaTortillaQRO.JPG", "coordinates": [445.5, 643.5, 505.5, 652.5]}, {"uri": "https://en.wikipedia.org/wiki/File:Mexican_rice_and_beans.jpg", "coordinates": [445.5, 712.5, 505.5, 721.5]}, {"uri": "https://en.wikipedia.org/wiki/Arroz_a_la_tumbada", "coordinates": [171.0, 584.25, 242.25, 593.25]}, {"uri": "https://en.wikipedia.org/wiki/White_rice", "coordinates": [250.5, 584.25, 297.75, 593.25]}, {"uri": "https://en.wikipedia.org/wiki/Arroz_negro_(Mexican_cuisine)", "coordinates": [306.0, 584.25, 350.25, 593.25]}, {"uri": "https://en.wikipedia.org/wiki/Arroz_poblano", "coordinates": [357.75, 584.25, 410.25, 593.25]}, {"uri": "https://en.wikipedia.org/wiki/Mexican_rice", "coordinates": [171.0, 597.0, 207.0, 606.0]}, {"uri": "https://en.wikipedia.org/wiki/Morisqueta", "coordinates": [216.0, 597.0, 258.0, 606.0]}, {"uri": "https://en.wikipedia.org/wiki/Borracho_beans", "coordinates": [171.0, 612.0, 231.0, 621.0]}, {"uri": "https://en.wikipedia.org/wiki/Frijoles_charros", "coordinates": [240.0, 612.0, 298.5, 621.0]}, {"uri": "https://en.wikipedia.org/wiki/Frijoles_negros", "coordinates": [306.0, 612.0, 362.25, 621.0]}, {"uri": "https://en.wikipedia.org/wiki/Frijoles_Puercos", "coordinates": [370.5, 612.0, 431.25, 621.0]}, {"uri": "https://en.wikipedia.org/wiki/Refried_beans", "coordinates": [171.0, 624.75, 224.25, 633.75]}, {"uri": "https://en.wikipedia.org/wiki/Huevos_a_la_mexicana", "coordinates": [171.0, 639.75, 252.75, 648.75]}, {"uri": "https://en.wikipedia.org/wiki/Huevos_divorciados", "coordinates": [261.0, 639.75, 334.5, 648.75]}, {"uri": "https://en.wikipedia.org/wiki/Huevos_motule%25C3%25B1os", "coordinates": [342.75, 639.75, 411.75, 648.75]}, {"uri": "https://en.wikipedia.org/wiki/Huevos_rancheros", "coordinates": [171.0, 651.75, 240.0, 660.75]}, {"uri": "https://en.wikipedia.org/wiki/Machacado_con_huevo", "coordinates": [248.25, 651.75, 333.75, 660.75]}, {"uri": "https://en.wikipedia.org/wiki/Chile_relleno", "coordinates": [171.0, 666.75, 218.25, 675.75]}, {"uri": "https://en.wikipedia.org/wiki/Escabeche", "coordinates": [226.5, 666.75, 305.25, 675.75]}, {"uri": "https://en.wikipedia.org/wiki/Chiles_en_nogada", "coordinates": [313.5, 666.75, 379.5, 675.75]}, {"uri": "https://en.wikipedia.org/wiki/Chipotle", "coordinates": [387.75, 666.75, 418.5, 675.75]}, {"uri": "https://en.wikipedia.org/wiki/Elote", "coordinates": [171.0, 679.5, 189.75, 688.5]}, {"uri": "https://en.wikipedia.org/wiki/Esquites", "coordinates": [198.0, 679.5, 230.25, 688.5]}, {"uri": "https://en.wikipedia.org/wiki/Guasanas", "coordinates": [238.5, 679.5, 277.5, 688.5]}, {"uri": "https://en.wikipedia.org/wiki/Nopal", "coordinates": [285.0, 679.5, 332.25, 688.5]}, {"uri": "https://en.wikipedia.org/wiki/Rajas_con_crema", "coordinates": [340.5, 679.5, 403.5, 688.5]}, {"uri": "https://en.wikipedia.org/wiki/Romeritos", "coordinates": [171.0, 692.25, 209.25, 701.25]}, {"uri": "https://en.wikipedia.org/wiki/Tortita_(Mexican_food)", "coordinates": [217.5, 692.25, 275.25, 701.25]}]}, {"hyperlinks": [{"uri": "https://en.wikipedia.org/wiki/File:Day_of_the_Dead_Coyoacan_2014_-_63.JPG", "coordinates": [445.5, 159.0, 505.5, 168.0]}, {"uri": "https://en.wikipedia.org/wiki/File:Ela_huevos_rancheros.jpg", "coordinates": [445.5, 213.0, 505.5, 222.0]}, {"uri": "https://en.wikipedia.org/wiki/File:Es_uno_de_los_platillos_principales_de_la_temporada_de_cuaresma.jpg", "coordinates": [445.5, 266.25, 505.5, 275.25]}, {"uri": "https://en.wikipedia.org/wiki/File:A_Green_Meal_(0034).jpg", "coordinates": [445.5, 319.5, 505.5, 328.5]}, {"uri": "https://en.wikipedia.org/wiki/File:AporreadilloUruapan.JPG", "coordinates": [445.5, 370.5, 505.5, 379.5]}, {"uri": "https://en.wikipedia.org/wiki/File:MojarraFritoJanitizio.JPG", "coordinates": [445.5, 417.0, 505.5, 426.0]}, {"uri": "https://en.wikipedia.org/wiki/File:Pescado_a_la_talla.jpg", "coordinates": [445.5, 483.0, 505.5, 492.0]}, {"uri": "https://en.wikipedia.org/wiki/File:Mole_in_Puebla.JPG", "coordinates": [445.5, 552.0, 505.5, 561.0]}, {"uri": "https://en.wikipedia.org/wiki/File:Flautas_guacamole_tortillas.jpg", "coordinates": [445.5, 603.75, 505.5, 612.75]}, {"uri": "https://en.wikipedia.org/wiki/File:Concha_(pan_dulce_mexicano)_01.JPG", "coordinates": [445.5, 651.0, 505.5, 660.0]}, {"uri": "https://en.wikipedia.org/wiki/Al_pastor", "coordinates": [171.0, 147.0, 204.0, 156.0]}, {"uri": "https://en.wikipedia.org/wiki/Barbacoa", "coordinates": [213.0, 147.0, 249.0, 156.0]}, {"uri": "https://en.wikipedia.org/wiki/Cabrito", "coordinates": [257.25, 147.0, 284.25, 156.0]}, {"uri": "https://en.wikipedia.org/wiki/Discada", "coordinates": [292.5, 147.0, 322.5, 156.0]}, {"uri": "https://en.wikipedia.org/wiki/Entomatada", "coordinates": [330.75, 147.0, 375.75, 156.0]}, {"uri": "https://en.wikipedia.org/wiki/Mixiote", "coordinates": [384.0, 147.0, 409.5, 156.0]}, {"uri": "https://en.wikipedia.org/wiki/Moronga", "coordinates": [171.0, 159.0, 204.0, 168.0]}, {"uri": "https://en.wikipedia.org/wiki/Pastel_azteca", "coordinates": [213.0, 159.0, 263.25, 168.0]}, {"uri": "https://en.wikipedia.org/wiki/Relleno_negro", "coordinates": [270.75, 159.0, 324.0, 168.0]}, {"uri": "https://en.wikipedia.org/wiki/Tripas", "coordinates": [332.25, 159.0, 356.25, 168.0]}, {"uri": "https://en.wikipedia.org/wiki/Arroz_con_pollo", "coordinates": [224.25, 175.5, 280.5, 184.5]}, {"uri": "https://en.wikipedia.org/wiki/Chicken_feet", "coordinates": [288.0, 175.5, 313.5, 184.5]}, {"uri": "https://en.wikipedia.org/wiki/Escabeche_oriental", "coordinates": [321.75, 175.5, 393.75, 184.5]}, {"uri": "https://en.wikipedia.org/wiki/Mole_poblano", "coordinates": [224.25, 188.25, 275.25, 197.25]}, {"uri": "https://en.wikipedia.org/wiki/Pollo_motule%25C3%25B1o", "coordinates": [282.75, 188.25, 338.25, 197.25]}, {"uri": "https://en.wikipedia.org/wiki/Tinga_(dish)", "coordinates": [346.5, 188.25, 400.5, 197.25]}, {"uri": "https://en.wikipedia.org/wiki/Adobada", "coordinates": [224.25, 203.25, 258.0, 212.25]}, {"uri": "https://en.wikipedia.org/wiki/Calabacitas_con_puerco", "coordinates": [266.25, 203.25, 355.5, 212.25]}, {"uri": "https://en.wikipedia.org/wiki/Carne_de_chango", "coordinates": [363.0, 203.25, 429.0, 212.25]}, {"uri": "https://en.wikipedia.org/wiki/Carnitas", "coordinates": [224.25, 216.0, 255.75, 225.0]}, {"uri": "https://en.wikipedia.org/wiki/Chicharr%25C3%25B3n_en_salsa", "coordinates": [264.0, 216.0, 339.75, 225.0]}, {"uri": "https://en.wikipedia.org/wiki/Chileajo_de_cerdo", "coordinates": [348.0, 216.0, 414.0, 225.0]}, {"uri": "https://en.wikipedia.org/wiki/Chilorio", "coordinates": [224.25, 228.0, 252.75, 237.0]}, {"uri": "https://en.wikipedia.org/wiki/Chorizo", "coordinates": [261.0, 228.0, 289.5, 237.0]}, {"uri": "https://en.wikipedia.org/wiki/Cochinita_pibil", "coordinates": [297.0, 228.0, 349.5, 237.0]}, {"uri": "https://en.wikipedia.org/wiki/Cueritos", "coordinates": [357.75, 228.0, 389.25, 237.0]}, {"uri": "https://en.wikipedia.org/wiki/Poc_chuc", "coordinates": [397.5, 228.0, 432.0, 237.0]}, {"uri": "https://en.wikipedia.org/wiki/Alambre", "coordinates": [224.25, 243.0, 255.0, 252.0]}, {"uri": "https://en.wikipedia.org/wiki/Aporreadillo", "coordinates": [263.25, 243.0, 308.25, 252.0]}, {"uri": "https://en.wikipedia.org/wiki/Meatball#Americas", "coordinates": [316.5, 243.0, 399.0, 252.0]}, {"uri": "https://en.wikipedia.org/wiki/Beef_brain", "coordinates": [224.25, 255.75, 263.25, 264.75]}, {"uri": "https://en.wikipedia.org/wiki/Beef_tongue", "coordinates": [270.75, 255.75, 316.5, 264.75]}, {"uri": "https://en.wikipedia.org/wiki/Cabeza", "coordinates": [324.75, 255.75, 353.25, 264.75]}, {"uri": "https://en.wikipedia.org/wiki/Carne_a_la_tampique%25C3%25B1a", "coordinates": [224.25, 268.5, 310.5, 277.5]}, {"uri": "https://en.wikipedia.org/wiki/Carne_asada", "coordinates": [318.0, 268.5, 366.75, 277.5]}, {"uri": "https://en.wikipedia.org/wiki/Carne_seca", "coordinates": [375.0, 268.5, 418.5, 277.5]}, {"uri": "https://en.wikipedia.org/wiki/Criadillas", "coordinates": [224.25, 281.25, 258.75, 290.25]}, {"uri": "https://en.wikipedia.org/wiki/Machaca", "coordinates": [267.0, 281.25, 300.75, 290.25]}, {"uri": "https://en.wikipedia.org/wiki/Milanesa", "coordinates": [309.0, 281.25, 342.0, 290.25]}, {"uri": "https://en.wikipedia.org/wiki/Pachola", "coordinates": [350.25, 281.25, 380.25, 290.25]}, {"uri": "https://en.wikipedia.org/wiki/Picadillo", "coordinates": [388.5, 281.25, 419.25, 290.25]}, {"uri": "https://en.wikipedia.org/wiki/Puntas_(Mexican_dish)", "coordinates": [224.25, 294.0, 250.5, 303.0]}, {"uri": "https://en.wikipedia.org/wiki/Quesabirria", "coordinates": [258.0, 294.0, 302.25, 303.0]}, {"uri": "https://en.wikipedia.org/wiki/Salpicon", "coordinates": [310.5, 294.0, 342.75, 303.0]}, {"uri": "https://en.wikipedia.org/wiki/Tinga_(dish)", "coordinates": [351.0, 294.0, 399.0, 303.0]}, {"uri": "https://en.wikipedia.org/wiki/Aguachile", "coordinates": [224.25, 309.0, 261.0, 318.0]}, {"uri": "https://en.wikipedia.org/wiki/Cahuamanta", "coordinates": [269.25, 309.0, 317.25, 318.0]}, {"uri": "https://en.wikipedia.org/wiki/Camarones_al_ajillo", "coordinates": [325.5, 309.0, 397.5, 318.0]}, {"uri": "https://en.wikipedia.org/wiki/Ceviche", "coordinates": [405.0, 309.0, 435.0, 318.0]}, {"uri": "https://en.wikipedia.org/wiki/Huachinango_a_la_Veracruzana", "coordinates": [224.25, 321.0, 340.5, 330.0]}, {"uri": "https://en.wikipedia.org/wiki/Mixmole_de_pescado", "coordinates": [348.0, 321.0, 424.5, 330.0]}, {"uri": "https://en.wikipedia.org/wiki/Mojarra_frita", "coordinates": [224.25, 333.75, 269.25, 342.75]}, {"uri": "https://en.wikipedia.org/wiki/Pan_de_caz%25C3%25B3n", "coordinates": [277.5, 333.75, 328.5, 342.75]}, {"uri": "https://en.wikipedia.org/wiki/Pescadito", "coordinates": [336.75, 333.75, 373.5, 342.75]}, {"uri": "https://en.wikipedia.org/wiki/Pescado_al_ajillo", "coordinates": [224.25, 346.5, 285.0, 355.5]}, {"uri": "https://en.wikipedia.org/w/index.php?title=Pescado_a_la_talla&action=edit&redlink=1", "coordinates": [293.25, 346.5, 360.0, 355.5]}, {"uri": "https://en.wikipedia.org/wiki/Pulpo_a_la_campechana", "coordinates": [224.25, 359.25, 312.75, 368.25]}, {"uri": "https://en.wikipedia.org/wiki/Chahuis", "coordinates": [171.0, 390.75, 201.75, 399.75]}, {"uri": "https://en.wikipedia.org/wiki/Chapulines", "coordinates": [210.0, 390.75, 252.0, 399.75]}, {"uri": "https://en.wikipedia.org/wiki/Escamol", "coordinates": [261.0, 390.75, 301.5, 399.75]}, {"uri": "https://en.wikipedia.org/wiki/Corn_smut", "coordinates": [309.0, 390.75, 352.5, 399.75]}, {"uri": "https://en.wikipedia.org/wiki/Jumiles", "coordinates": [360.75, 390.75, 387.75, 399.75]}, {"uri": "https://en.wikipedia.org/wiki/Maguey_worm", "coordinates": [171.0, 403.5, 222.75, 412.5]}, {"uri": "https://en.wikipedia.org/wiki/Chicharr%25C3%25B3n_de_queso", "coordinates": [171.0, 420.75, 250.5, 429.75]}, {"uri": "https://en.wikipedia.org/wiki/Quesadilla", "coordinates": [258.75, 420.75, 298.5, 429.75]}, {"uri": "https://en.wikipedia.org/wiki/Queso_en_salsa", "coordinates": [306.75, 420.75, 366.0, 429.75]}, {"uri": "https://en.wikipedia.org/wiki/Queso_flameado", "coordinates": [374.25, 420.75, 436.5, 429.75]}, {"uri": "https://en.wikipedia.org/wiki/Mexican_street_food", "coordinates": [123.0, 489.75, 159.75, 498.75]}, {"uri": "https://en.wikipedia.org/wiki/Empalme_(food)", "coordinates": [171.0, 437.25, 205.5, 446.25]}, {"uri": "https://en.wikipedia.org/wiki/Enchilada", "coordinates": [213.75, 437.25, 250.5, 446.25]}, {"uri": "https://en.wikipedia.org/wiki/Guajolota", "coordinates": [258.75, 437.25, 294.75, 446.25]}, {"uri": "https://en.wikipedia.org/wiki/Nachos", "coordinates": [303.0, 437.25, 330.75, 446.25]}, {"uri": "https://en.wikipedia.org/wiki/Quesadilla", "coordinates": [339.0, 437.25, 378.75, 446.25]}, {"uri": "https://en.wikipedia.org/wiki/Taco", "coordinates": [387.0, 437.25, 405.75, 446.25]}, {"uri": "https://en.wikipedia.org/wiki/Taquito", "coordinates": [171.0, 450.0, 199.5, 459.0]}, {"uri": "https://en.wikipedia.org/wiki/Cazuelita", "coordinates": [245.25, 465.0, 279.75, 474.0]}, {"uri": "https://en.wikipedia.org/wiki/Chalupa", "coordinates": [288.0, 465.0, 319.5, 474.0]}, {"uri": "https://en.wikipedia.org/wiki/Chilaquiles", "coordinates": [327.0, 465.0, 368.25, 474.0]}, {"uri": "https://en.wikipedia.org/wiki/Chimichanga", "coordinates": [376.5, 465.0, 425.25, 474.0]}, {"uri": "https://en.wikipedia.org/wiki/Chochoyote", "coordinates": [245.25, 477.0, 290.25, 486.0]}, {"uri": "https://en.wikipedia.org/wiki/Corn_tortilla", "coordinates": [298.5, 477.0, 342.0, 486.0]}, {"uri": "https://en.wikipedia.org/wiki/Corunda", "coordinates": [350.25, 477.0, 383.25, 486.0]}, {"uri": "https://en.wikipedia.org/wiki/Doblada_(Mexican_cuisine)", "coordinates": [390.75, 477.0, 422.25, 486.0]}, {"uri": "https://en.wikipedia.org/wiki/Duros_(food)", "coordinates": [245.25, 489.75, 267.75, 498.75]}, {"uri": "https://en.wikipedia.org/wiki/Gordita", "coordinates": [276.0, 489.75, 303.75, 498.75]}, {"uri": "https://en.wikipedia.org/wiki/Huarache_(food)", "coordinates": [312.0, 489.75, 348.0, 498.75]}, {"uri": "https://en.wikipedia.org/wiki/Molote", "coordinates": [356.25, 489.75, 381.0, 498.75]}, {"uri": "https://en.wikipedia.org/wiki/Panucho", "coordinates": [389.25, 489.75, 422.25, 498.75]}, {"uri": "https://en.wikipedia.org/wiki/Papadzules", "coordinates": [245.25, 502.5, 288.75, 511.5]}, {"uri": "https://en.wikipedia.org/wiki/Piedra_(Mexican_cuisine)", "coordinates": [297.0, 502.5, 321.0, 511.5]}, {"uri": "https://en.wikipedia.org/wiki/Salbut", "coordinates": [329.25, 502.5, 353.25, 511.5]}, {"uri": "https://en.wikipedia.org/wiki/Sope_(food)", "coordinates": [360.75, 502.5, 380.25, 511.5]}, {"uri": "https://en.wikipedia.org/wiki/Memela", "coordinates": [393.0, 502.5, 422.25, 511.5]}, {"uri": "https://en.wikipedia.org/wiki/Tamale", "coordinates": [245.25, 515.25, 273.0, 524.25]}, {"uri": "https://en.wikipedia.org/wiki/Tlacoyo", "coordinates": [281.25, 515.25, 311.25, 524.25]}, {"uri": "https://en.wikipedia.org/wiki/Tlayuda", "coordinates": [318.75, 515.25, 348.75, 524.25]}, {"uri": "https://en.wikipedia.org/wiki/Tostada_(tortilla)", "coordinates": [357.0, 515.25, 387.75, 524.25]}, {"uri": "https://en.wikipedia.org/wiki/Totopo", "coordinates": [396.0, 515.25, 423.0, 524.25]}, {"uri": "https://en.wikipedia.org/wiki/Burrito", "coordinates": [245.25, 530.25, 270.0, 539.25]}, {"uri": "https://en.wikipedia.org/wiki/Cemita", "coordinates": [278.25, 530.25, 304.5, 539.25]}, {"uri": "https://en.wikipedia.org/wiki/Gringas", "coordinates": [312.0, 530.25, 342.0, 539.25]}, {"uri": "https://en.wikipedia.org/wiki/Mollete", "coordinates": [350.25, 530.25, 377.25, 539.25]}, {"uri": "https://en.wikipedia.org/wiki/Pambazo", "coordinates": [384.75, 530.25, 419.25, 539.25]}, {"uri": "https://en.wikipedia.org/wiki/Paste_(pasty)", "coordinates": [245.25, 543.0, 266.25, 552.0]}, {"uri": "https://en.wikipedia.org/wiki/Sincronizada", "coordinates": [274.5, 543.0, 322.5, 552.0]}, {"uri": "https://en.wikipedia.org/wiki/Torta#Mexican_sandwich", "coordinates": [330.75, 543.0, 351.0, 552.0]}, {"uri": "https://en.wikipedia.org/wiki/Flour_tortilla", "coordinates": [359.25, 543.0, 408.75, 552.0]}, {"uri": "https://en.wikipedia.org/wiki/Adobo", "coordinates": [171.0, 558.75, 195.0, 567.75]}, {"uri": "https://en.wikipedia.org/wiki/Mole_(sauce)", "coordinates": [204.0, 558.75, 222.0, 567.75]}, {"uri": "https://en.wikipedia.org/wiki/Mole_blanco", "coordinates": [227.25, 558.75, 272.25, 567.75]}, {"uri": "https://en.wikipedia.org/wiki/Mole_poblano", "coordinates": [280.5, 558.75, 331.5, 567.75]}, {"uri": "https://en.wikipedia.org/wiki/Mole_verde", "coordinates": [339.0, 558.75, 381.0, 567.75]}, {"uri": "https://en.wikipedia.org/wiki/Recado_rojo", "coordinates": [392.25, 558.75, 438.0, 567.75]}, {"uri": "https://en.wikipedia.org/wiki/Salsa_(sauce)", "coordinates": [177.0, 571.5, 198.0, 580.5]}, {"uri": "https://en.wikipedia.org/wiki/Salsa_roja", "coordinates": [203.25, 571.5, 240.75, 580.5]}, {"uri": "https://en.wikipedia.org/wiki/Salsa_verde", "coordinates": [249.0, 571.5, 294.0, 580.5]}, {"uri": "https://en.wikipedia.org/wiki/Agave_syrup", "coordinates": [171.0, 588.0, 218.25, 597.0]}, {"uri": "https://en.wikipedia.org/wiki/Alegr%25C3%25ADa_(Mexican_candy)", "coordinates": [226.5, 588.0, 253.5, 597.0]}, {"uri": "https://en.wikipedia.org/wiki/Alfajor", "coordinates": [261.0, 588.0, 285.0, 597.0]}, {"uri": "https://en.wikipedia.org/wiki/Rice_pudding", "coordinates": [293.25, 588.0, 351.75, 597.0]}, {"uri": "https://en.wikipedia.org/wiki/Bionico", "coordinates": [360.0, 588.0, 387.0, 597.0]}, {"uri": "https://en.wikipedia.org/wiki/Swiss_roll#Spain", "coordinates": [395.25, 588.0, 442.5, 597.0]}, {"uri": "https://en.wikipedia.org/wiki/Cajeta_de_Celaya", "coordinates": [177.0, 600.75, 242.25, 609.75]}, {"uri": "https://en.wikipedia.org/wiki/Capirotada", "coordinates": [249.75, 600.75, 291.75, 609.75]}, {"uri": "https://en.wikipedia.org/wiki/Chongos_zamoranos", "coordinates": [300.0, 600.75, 378.0, 609.75]}, {"uri": "https://en.wikipedia.org/wiki/Churro", "coordinates": [385.5, 600.75, 415.5, 609.75]}, {"uri": "https://en.wikipedia.org/wiki/Cocada", "coordinates": [171.0, 612.75, 200.25, 621.75]}, {"uri": "https://en.wikipedia.org/wiki/Coyotas", "coordinates": [208.5, 612.75, 239.25, 621.75]}, {"uri": "https://en.wikipedia.org/wiki/Cr%25C3%25A8me_caramel", "coordinates": [247.5, 612.75, 298.5, 621.75]}, {"uri": "https://en.wikipedia.org/wiki/Dulce_de_leche", "coordinates": [306.75, 612.75, 363.0, 621.75]}, {"uri": "https://en.wikipedia.org/wiki/Fried_ice_cream", "coordinates": [371.25, 612.75, 429.75, 621.75]}, {"uri": "https://en.wikipedia.org/wiki/Mango", "coordinates": [171.0, 625.5, 232.5, 634.5]}, {"uri": "https://en.wikipedia.org/wiki/Marquesita", "coordinates": [240.75, 625.5, 282.75, 634.5]}, {"uri": "https://en.wikipedia.org/wiki/Marzipan", "coordinates": [291.0, 625.5, 324.75, 634.5]}, {"uri": "https://en.wikipedia.org/wiki/Nicuatole", "coordinates": [333.0, 625.5, 367.5, 634.5]}, {"uri": "https://en.wikipedia.org/wiki/Palmier", "coordinates": [375.0, 625.5, 399.75, 634.5]}, {"uri": "https://en.wikipedia.org/wiki/Panela", "coordinates": [408.0, 625.5, 434.25, 634.5]}, {"uri": "https://en.wikipedia.org/wiki/Polvor%25C3%25B3n", "coordinates": [171.0, 638.25, 204.0, 647.25]}, {"uri": "https://en.wikipedia.org/wiki/Tres_leches_cake", "coordinates": [213.0, 638.25, 277.5, 647.25]}, {"uri": "https://en.wikipedia.org/wiki/Turr%25C3%25B3n", "coordinates": [285.0, 638.25, 310.5, 647.25]}, {"uri": "https://en.wikipedia.org/wiki/Caesar_salad", "coordinates": [171.0, 654.75, 221.25, 663.75]}, {"uri": "https://en.wikipedia.org/wiki/Curtido", "coordinates": [229.5, 654.75, 256.5, 663.75]}, {"uri": "https://en.wikipedia.org/wiki/Nopalito", "coordinates": [264.75, 654.75, 299.25, 663.75]}, {"uri": "https://en.wikipedia.org/wiki/Pico_de_gallo", "coordinates": [362.25, 654.75, 410.25, 663.75]}, {"uri": "https://en.wikipedia.org/wiki/Mexican_breads", "coordinates": [129.75, 676.5, 159.75, 685.5]}, {"uri": "https://en.wikipedia.org/wiki/Bolillo", "coordinates": [171.0, 670.5, 192.75, 679.5]}, {"uri": "https://en.wikipedia.org/wiki/Bu%25C3%25B1uelo", "coordinates": [201.0, 670.5, 231.75, 679.5]}, {"uri": "https://en.wikipedia.org/wiki/Cemita", "coordinates": [240.0, 670.5, 266.25, 679.5]}, {"uri": "https://en.wikipedia.org/wiki/Cochinito_de_piloncillo", "coordinates": [274.5, 670.5, 356.25, 679.5]}, {"uri": "https://en.wikipedia.org/wiki/Cocol", "coordinates": [364.5, 670.5, 385.5, 679.5]}, {"uri": "https://en.wikipedia.org/wiki/Concha", "coordinates": [393.75, 670.5, 423.0, 679.5]}, {"uri": "https://en.wikipedia.org/wiki/Pan_de_muerto", "coordinates": [171.0, 683.25, 226.5, 692.25]}, {"uri": "https://en.wikipedia.org/wiki/Pan_dulce", "coordinates": [234.75, 683.25, 272.25, 692.25]}, {"uri": "https://en.wikipedia.org/wiki/Rosca", "coordinates": [280.5, 683.25, 304.5, 692.25]}, {"uri": "https://en.wikipedia.org/wiki/Rosca_de_reyes", "coordinates": [309.75, 683.25, 342.75, 692.25]}, {"uri": "https://en.wikipedia.org/wiki/Agua_de_Jamaica", "coordinates": [171.0, 698.25, 235.5, 707.25]}, {"uri": "https://en.wikipedia.org/wiki/Atole", "coordinates": [243.75, 698.25, 262.5, 707.25]}, {"uri": "https://en.wikipedia.org/wiki/Beer_in_Mexico", "coordinates": [270.75, 698.25, 288.75, 707.25]}, {"uri": "https://en.wikipedia.org/wiki/Caf%25C3%25A9_de_olla", "coordinates": [297.0, 698.25, 342.0, 707.25]}, {"uri": "https://en.wikipedia.org/wiki/Chamoyada", "coordinates": [350.25, 698.25, 395.25, 707.25]}, {"uri": "https://en.wikipedia.org/wiki/Champurrado", "coordinates": [171.0, 711.0, 222.75, 720.0]}, {"uri": "https://en.wikipedia.org/wiki/Curado_(drink)", "coordinates": [231.0, 711.0, 258.75, 720.0]}, {"uri": "https://en.wikipedia.org/wiki/Horchata", "coordinates": [267.0, 711.0, 300.75, 720.0]}, {"uri": "https://en.wikipedia.org/wiki/Licuado", "coordinates": [309.0, 711.0, 339.0, 720.0]}, {"uri": "https://en.wikipedia.org/wiki/Margarita", "coordinates": [347.25, 711.0, 383.25, 720.0]}, {"uri": "https://en.wikipedia.org/wiki/Mexican_tea_culture", "coordinates": [171.0, 723.75, 243.75, 732.75]}, {"uri": "https://en.wikipedia.org/wiki/Ponche", "coordinates": [252.0, 723.75, 280.5, 732.75]}, {"uri": "https://en.wikipedia.org/wiki/Popo_(beverage)", "coordinates": [288.75, 723.75, 308.25, 732.75]}, {"uri": "https://en.wikipedia.org/wiki/Pozol", "coordinates": [316.5, 723.75, 336.75, 732.75]}, {"uri": "https://en.wikipedia.org/wiki/Tascalate", "coordinates": [345.0, 723.75, 381.75, 732.75]}, {"uri": "https://en.wikipedia.org/wiki/Tejate", "coordinates": [390.0, 723.75, 414.0, 732.75]}]}, {"hyperlinks": [{"uri": "https://en.wikipedia.org/wiki/Cuisine_of_Chiapas", "coordinates": [275.25, 147.75, 306.0, 156.75]}, {"uri": "https://en.wikipedia.org/wiki/Oaxacan_cuisine", "coordinates": [314.25, 147.75, 342.75, 156.75]}, {"uri": "https://en.wikipedia.org/wiki/Cuisine_of_Mexico_City", "coordinates": [351.0, 147.75, 393.0, 156.75]}, {"uri": "https://en.wikipedia.org/wiki/Cuisine_of_Veracruz", "coordinates": [401.25, 147.75, 434.25, 156.75]}, {"uri": "https://en.wikipedia.org/wiki/Mexican-American_cuisine", "coordinates": [275.25, 164.25, 310.5, 173.25]}, {"uri": "https://en.wikipedia.org/wiki/Korean-Mexican_fusion", "coordinates": [315.75, 164.25, 376.5, 173.25]}, {"uri": "https://en.wikipedia.org/wiki/New_Mexican_cuisine", "coordinates": [384.75, 164.25, 432.75, 173.25]}, {"uri": "https://en.wikipedia.org/wiki/Tex-Mex", "coordinates": [275.25, 177.0, 306.75, 186.0]}, {"uri": "https://en.wikipedia.org/wiki/Baja_Med", "coordinates": [318.0, 177.0, 353.25, 186.0]}, {"uri": "https://en.wikipedia.org/wiki/Aztec_cuisine", "coordinates": [275.25, 192.75, 295.5, 201.75]}, {"uri": "https://en.wikipedia.org/wiki/Ancient_Maya_cuisine", "coordinates": [303.0, 192.75, 323.25, 201.75]}, {"uri": "https://en.wikipedia.org/wiki/Comal_(cookware)", "coordinates": [120.0, 209.25, 144.0, 218.25]}, {"uri": "https://en.wikipedia.org/wiki/Escuela_de_Gastronom%25C3%25ADa_Mexicana", "coordinates": [151.5, 209.25, 283.5, 218.25]}, {"uri": "https://en.wikipedia.org/wiki/Taco_stand", "coordinates": [291.0, 209.25, 333.75, 218.25]}, {"uri": "https://en.wikipedia.org/wiki/Chocolate", "coordinates": [341.25, 209.25, 380.25, 218.25]}, {"uri": "https://en.wikipedia.org/wiki/Vanilla", "coordinates": [387.0, 209.25, 412.5, 218.25]}, {"uri": "https://en.wikipedia.org/wiki/File:Foodlogo2.svg", "coordinates": [118.5, 225.75, 128.25, 234.75]}, {"uri": "https://en.wikipedia.org/wiki/Portal:Food", "coordinates": [130.5, 225.75, 174.75, 234.75]}, {"uri": "https://en.wikipedia.org/wiki/Portal:Mexico", "coordinates": [195.0, 225.75, 245.25, 234.75]}, {"uri": "https://en.wikipedia.org/wiki/Category:Mexican_cuisine", "coordinates": [264.75, 225.75, 300.0, 234.75]}, {"uri": "https://commons.wikimedia.org/wiki/Category:Cuisine_of_Mexico", "coordinates": [317.25, 225.75, 355.5, 234.75]}, {"uri": "https://en.wikipedia.org/wiki/File:Wikibooks-logo.svg", "coordinates": [363.0, 225.75, 372.75, 234.75]}, {"uri": "https://en.wikibooks.org/wiki/Cookbook:Cuisine_of_Mexico", "coordinates": [375.0, 225.75, 414.0, 234.75]}, {"uri": "https://en.wikipedia.org/wiki/Wikipedia:WikiProject_Food_and_drink", "coordinates": [432.75, 225.75, 474.75, 234.75]}, {"uri": "https://en.wikipedia.org/wiki/Help:Category", "coordinates": [89.25, 256.5, 135.75, 267.0]}, {"uri": "https://en.wikipedia.org/wiki/Category:Condiments", "coordinates": [143.25, 256.5, 193.5, 267.0]}, {"uri": "https://en.wikipedia.org/wiki/Category:Cuisine_of_the_Southwestern_United_States", "coordinates": [203.25, 256.5, 377.25, 267.0]}, {"uri": "https://en.wikipedia.org/wiki/Category:Dips_(food)", "coordinates": [387.0, 256.5, 433.5, 267.0]}, {"uri": "https://en.wikipedia.org/wiki/Category:Guatemalan_cuisine", "coordinates": [93.75, 270.75, 175.5, 281.25]}, {"uri": "https://en.wikipedia.org/wiki/Category:Mexican_cuisine", "coordinates": [186.0, 270.75, 252.0, 281.25]}, {"uri": "https://en.wikipedia.org/wiki/Category:Mexican_garnish", "coordinates": [261.75, 270.75, 329.25, 281.25]}, {"uri": "https://en.wikipedia.org/wiki/Category:New_Mexican_cuisine", "coordinates": [339.0, 270.75, 426.0, 281.25]}, {"uri": "https://en.wikipedia.org/wiki/Category:Tex-Mex_cuisine", "coordinates": [93.75, 285.0, 160.5, 295.5]}, {"uri": "https://en.wikipedia.org/wiki/Category:Vegan_cuisine", "coordinates": [171.0, 285.0, 230.25, 295.5]}, {"uri": "https://en.wikipedia.org/wiki/Category:Vegetable_dishes", "coordinates": [240.0, 285.0, 312.75, 295.5]}, {"uri": "https://en.wikipedia.org/wiki/Category:Avocado_dishes", "coordinates": [322.5, 285.0, 389.25, 295.5]}, {"uri": "https://en.wikipedia.org/wiki/Wikipedia:Text_of_the_Creative_Commons_Attribution-ShareAlike_4.0_International_License", "coordinates": [173.25, 358.5, 349.5, 367.5]}, {"uri": "https://foundation.wikimedia.org/wiki/Special:MyLanguage/Policy:Terms_of_Use", "coordinates": [140.25, 368.25, 185.25, 377.25]}, {"uri": "https://foundation.wikimedia.org/wiki/Special:MyLanguage/Policy:Privacy_policy", "coordinates": [201.0, 368.25, 244.5, 377.25]}, {"uri": "https://www.wikimediafoundation.org/", "coordinates": [393.0, 368.25, 481.5, 377.25]}, {"uri": "https://foundation.wikimedia.org/wiki/Special:MyLanguage/Policy:Privacy_policy", "coordinates": [86.25, 396.75, 129.0, 405.75]}, {"uri": "https://en.wikipedia.org/wiki/Wikipedia:About", "coordinates": [136.5, 396.75, 189.0, 405.75]}, {"uri": "https://en.wikipedia.org/wiki/Wikipedia:General_disclaimer", "coordinates": [196.5, 396.75, 236.25, 405.75]}, {"uri": "https://en.wikipedia.org/wiki/Wikipedia:Contact_us", "coordinates": [243.75, 396.75, 303.0, 405.75]}, {"uri": "https://foundation.wikimedia.org/wiki/Special:MyLanguage/Policy:Universal_Code_of_Conduct", "coordinates": [310.5, 396.75, 365.25, 405.75]}, {"uri": "https://developer.wikimedia.org", "coordinates": [372.75, 396.75, 410.25, 405.75]}, {"uri": "https://stats.wikimedia.org/#/en.wikipedia.org", "coordinates": [417.75, 396.75, 447.75, 405.75]}, {"uri": "https://foundation.wikimedia.org/wiki/Special:MyLanguage/Policy:Cookie_statement", "coordinates": [86.25, 418.5, 144.0, 427.5]}, {"uri": "https://en.m.wikipedia.org/w/index.php?title=Guacamole&mobileaction=toggle_view_mobile", "coordinates": [151.5, 418.5, 189.0, 427.5]}, {"uri": "https://wikimediafoundation.org/", "coordinates": [399.0, 418.5, 451.5, 427.5]}, {"uri": "https://www.mediawiki.org/", "coordinates": [455.25, 418.5, 507.75, 427.5]}]}]}